bcdcounter.v

// count till max_count

module bcd_counter#(
    parameter MAX_COUNT = 4'd9
) (
    input trigger,
    input rst,
    input set,
    input wire[3:0] set_value,
    output reg[3:0] counter,
    output reg overflow
);

    always @ (rst) begin : BCD_CRST
        counter <= 0;
        overflow <= 0;
    end

    always @ (posedge trigger) begin : BCD_COUNT
        if(set) begin
            counter <= set_value;
            overflow <= 0;
        end
        else if(counter < MAX_COUNT) begin
            counter = counter + 1;
            overflow <= 0;
        end
        else if(counter >= MAX_COUNT) begin
            counter = 0;
            overflow <= 1;
        end
    end

endmodule

module hour_counter
(
    input trigger,
    input rst,
    input set,
    input mode_24h,
    input wire[3:0] set_h0,
    input wire[3:0] set_h1,
    input wire[3:0] set_am_pm,
    output reg[3:0] h0,
    output reg[3:0] h1,
    output reg am_pm,
    output reg overflow
);

    always @ (rst) begin : BCD_CRST
        h0 <= 0;
        h1 <= 0;
        am_pm  <= 0;
        overflow <= 0;
    end

    always @ (posedge trigger) begin : BCD_COUNT
        if(set) begin
            h0 <= set_h0;
            h1 <= set_h1;
            am_pm <= set_am_pm;
            overflow <= 0;
        end
        else if((h0 < 9 && h1 == 4'd0) || (h0 < 9 && h1 == 4'd1 && mode_24h) || (h0 < 2 && h1 == 4'd1 && !mode_24h) || (h0 < 4 && h1 == 4'd2 && mode_24h)) begin
            h0 = h0 + 1;
            overflow <= 0;
        end
        else begin
            h0 <= 0;
            if(mode_24h) begin
                if(h1 < 2) h1 <= h1 + 1;
                else h1 <= 0;
            end
            else begin
                if(h1 == 0) h1 <= 4'd1;
                else h1 <= 0;
            end
            overflow <= 1;
        end
    end

endmodule

module sclk #(parameter F_MINUS1 = 10) (input clk, input rst, output reg sec_clk);

    reg[31:0] counter;

    always @ (posedge clk) begin
        if(rst) begin
            counter <= 0;
            sec_clk <= 0;
        end
        else if(counter < F_MINUS1) begin
            counter <= counter + 1;
            sec_clk <= 0;
        end
        else if(counter >= F_MINUS1) begin
            counter <= 0;
            sec_clk <= 1;
        end
    end

endmodule

// h1 h2 : m1 m2 : s1 s2
// 1 + 4 + 3 + 4 + 3 + 4
// 19
module time_view
(
    input clk, 
    input rst,
    input mode_24h,
    input set_time,
    input set_alarm,
    input wire[1:0] alarm_id,
    input wire[19:0] stime,
    input wire[19:0] stime_alarm,
    output wire[19:0] hh_mm_ss
);

    wire sec_clk;
    wire bcd_clk[6];

    // clk frequency is 2 Hz
    sclk #(1) second_clk(.clk(clk), .rst(rst), .sec_clk(sec_clk));

    // convert bcd to binary for setting hours time
    wire[3:0] in_htime;
    assign in_htime = stime[18] * 10 + stime[17:14];

    // convert binary to bcd for output hours time
    wire[3:0] bin_htime;
    wire[3:0] htime_12h = bin_htime >= 12 ? (bin_htime > 10 ? bin_htime : bin_htime - 9) : bin_htime - 12;


    assign hh_mm_ss[17:14] = bin_htime > 20 ? (bin_htime > 10 ? bin_htime : bin_htime - 9) : bin_htime - 20;

    bcd_counter #(9) s0(.trigger(sec_clk),    .rst(rst), .set(set_time), .set_value(stime[3:0]), .counter(hh_mm_ss[3:0]), .overflow(bcd_clk[0]));
    bcd_counter #(5) s1(.trigger(bcd_clk[0]), .rst(rst), .set(set_time), .set_value(stime[6:4]), .counter(hh_mm_ss[6:4]), .overflow(bcd_clk[1]));

    bcd_counter #(9) m0(.trigger(bcd_clk[1]), .rst(rst), .set(set_time), .set_value(stime[10: 7]), .counter(hh_mm_ss[10: 7]), .overflow(bcd_clk[2]));
    bcd_counter #(5) m1(.trigger(bcd_clk[2]), .rst(rst), .set(set_time), .set_value(stime[13:11]), .counter(hh_mm_ss[13:11]), .overflow(bcd_clk[3]));

    bcd_counter #(23) h0(.trigger(bcd_clk[4]), .rst(rst), .set(set_time), .set_value(in_htime), .counter(bin_htime), .overflow(bcd_clk[2]));

//    always @ (posedge clk) begin
//        if(rst) begin
//            // reset all state
//            ;
//        end
//    end

endmodule

counter_tb.v

module counter_tb();

    reg clk = 0;
    reg rst = 1;
    reg set = 0;
    wire sec_clk;
    reg[3:0] rvalue = 0;
    wire[3:0] unit;
    wire[3:0] tens;
    wire sec_unit;
    wire sec_ten;
    always #1 clk = ~clk;

    sclk #(1) second_clk(.clk(clk), .rst(rst), .sec_clk(sec_clk));
    bcd_counter #(9) unitCounter(.trigger(sec_clk), .rst(rst), .set(set), .set_value(rvalue), .counter(unit), .overflow(sec_unit));
    bcd_counter #(5) tenCounter(.trigger(sec_unit), .rst(rst), .set(set), .set_value(rvalue), .counter(tens), .overflow(sec_ten));

    initial begin
        $dumpfile("counter.vcd");
        $dumpvars;
        
        // reset on first clock edge
        #2;
        rst = 0;

        #400;

        $finish;
    end

endmodule

counter.vcd
$date
	Tue Apr 23 21:40:10 2024
$end
$version
	Icarus Verilog
$end
$timescale
	1s
$end
$scope module counter_tb $end
$var wire 4 ! unit [3:0] $end
$var wire 4 " tens [3:0] $end
$var wire 1 # sec_unit $end
$var wire 1 $ sec_ten $end
$var wire 1 % sec_clk $end
$var reg 1 & clk $end
$var reg 1 ' rst $end
$var reg 4 ( rvalue [3:0] $end
$var reg 1 ) set $end
$scope module second_clk $end
$var wire 1 & clk $end
$var wire 1 ' rst $end
$var reg 32 * counter [31:0] $end
$var reg 1 % sec_clk $end
$upscope $end
$scope module tenCounter $end
$var wire 1 ' rst $end
$var wire 1 ) set $end
$var wire 4 + set_value [3:0] $end
$var wire 1 # trigger $end
$var reg 4 , counter [3:0] $end
$var reg 1 $ overflow $end
$scope begin BCD_COUNT $end
$upscope $end
$scope begin BCD_CRST $end
$upscope $end
$upscope $end
$scope module unitCounter $end
$var wire 1 ' rst $end
$var wire 1 ) set $end
$var wire 4 - set_value [3:0] $end
$var wire 1 % trigger $end
$var reg 4 . counter [3:0] $end
$var reg 1 # overflow $end
$scope begin BCD_COUNT $end
$upscope $end
$scope begin BCD_CRST $end
$upscope $end
$upscope $end
$upscope $end
$enddefinitions $end
#0
$dumpvars
b0 .
b0 -
b0 ,
b0 +
bx *
0)
b0 (
1'
0&
x%
0$
0#
b0 "
b0 !
$end
#1
0%
b0 *
1&
#2
0&
0'
#3
b1 *
1&
#4
0&
#5
b1 !
b1 .
1%
b0 *
1&
#6
0&
#7
0%
b1 *
1&
#8
0&
#9
b10 !
b10 .
1%
b0 *
1&
#10
0&
#11
0%
b1 *
1&
#12
0&
#13
b11 !
b11 .
1%
b0 *
1&
#14
0&
#15
0%
b1 *
1&
#16
0&
#17
b100 !
b100 .
1%
b0 *
1&
#18
0&
#19
0%
b1 *
1&
#20
0&
#21
b101 !
b101 .
1%
b0 *
1&
#22
0&
#23
0%
b1 *
1&
#24
0&
#25
b110 !
b110 .
1%
b0 *
1&
#26
0&
#27
0%
b1 *
1&
#28
0&
#29
b111 !
b111 .
1%
b0 *
1&
#30
0&
#31
0%
b1 *
1&
#32
0&
#33
b1000 !
b1000 .
1%
b0 *
1&
#34
0&
#35
0%
b1 *
1&
#36
0&
#37
b1001 !
b1001 .
1%
b0 *
1&
#38
0&
#39
0%
b1 *
1&
#40
0&
#41
b1 "
b1 ,
1#
b0 !
b0 .
1%
b0 *
1&
#42
0&
#43
0%
b1 *
1&
#44
0&
#45
0#
b1 !
b1 .
1%
b0 *
1&
#46
0&
#47
0%
b1 *
1&
#48
0&
#49
b10 !
b10 .
1%
b0 *
1&
#50
0&
#51
0%
b1 *
1&
#52
0&
#53
b11 !
b11 .
1%
b0 *
1&
#54
0&
#55
0%
b1 *
1&
#56
0&
#57
b100 !
b100 .
1%
b0 *
1&
#58
0&
#59
0%
b1 *
1&
#60
0&
#61
b101 !
b101 .
1%
b0 *
1&
#62
0&
#63
0%
b1 *
1&
#64
0&
#65
b110 !
b110 .
1%
b0 *
1&
#66
0&
#67
0%
b1 *
1&
#68
0&
#69
b111 !
b111 .
1%
b0 *
1&
#70
0&
#71
0%
b1 *
1&
#72
0&
#73
b1000 !
b1000 .
1%
b0 *
1&
#74
0&
#75
0%
b1 *
1&
#76
0&
#77
b1001 !
b1001 .
1%
b0 *
1&
#78
0&
#79
0%
b1 *
1&
#80
0&
#81
b10 "
b10 ,
1#
b0 !
b0 .
1%
b0 *
1&
#82
0&
#83
0%
b1 *
1&
#84
0&
#85
0#
b1 !
b1 .
1%
b0 *
1&
#86
0&
#87
0%
b1 *
1&
#88
0&
#89
b10 !
b10 .
1%
b0 *
1&
#90
0&
#91
0%
b1 *
1&
#92
0&
#93
b11 !
b11 .
1%
b0 *
1&
#94
0&
#95
0%
b1 *
1&
#96
0&
#97
b100 !
b100 .
1%
b0 *
1&
#98
0&
#99
0%
b1 *
1&
#100
0&
#101
b101 !
b101 .
1%
b0 *
1&
#102
0&
#103
0%
b1 *
1&
#104
0&
#105
b110 !
b110 .
1%
b0 *
1&
#106
0&
#107
0%
b1 *
1&
#108
0&
#109
b111 !
b111 .
1%
b0 *
1&
#110
0&
#111
0%
b1 *
1&
#112
0&
#113
b1000 !
b1000 .
1%
b0 *
1&
#114
0&
#115
0%
b1 *
1&
#116
0&
#117
b1001 !
b1001 .
1%
b0 *
1&
#118
0&
#119
0%
b1 *
1&
#120
0&
#121
b11 "
b11 ,
1#
b0 !
b0 .
1%
b0 *
1&
#122
0&
#123
0%
b1 *
1&
#124
0&
#125
0#
b1 !
b1 .
1%
b0 *
1&
#126
0&
#127
0%
b1 *
1&
#128
0&
#129
b10 !
b10 .
1%
b0 *
1&
#130
0&
#131
0%
b1 *
1&
#132
0&
#133
b11 !
b11 .
1%
b0 *
1&
#134
0&
#135
0%
b1 *
1&
#136
0&
#137
b100 !
b100 .
1%
b0 *
1&
#138
0&
#139
0%
b1 *
1&
#140
0&
#141
b101 !
b101 .
1%
b0 *
1&
#142
0&
#143
0%
b1 *
1&
#144
0&
#145
b110 !
b110 .
1%
b0 *
1&
#146
0&
#147
0%
b1 *
1&
#148
0&
#149
b111 !
b111 .
1%
b0 *
1&
#150
0&
#151
0%
b1 *
1&
#152
0&
#153
b1000 !
b1000 .
1%
b0 *
1&
#154
0&
#155
0%
b1 *
1&
#156
0&
#157
b1001 !
b1001 .
1%
b0 *
1&
#158
0&
#159
0%
b1 *
1&
#160
0&
#161
b100 "
b100 ,
1#
b0 !
b0 .
1%
b0 *
1&
#162
0&
#163
0%
b1 *
1&
#164
0&
#165
0#
b1 !
b1 .
1%
b0 *
1&
#166
0&
#167
0%
b1 *
1&
#168
0&
#169
b10 !
b10 .
1%
b0 *
1&
#170
0&
#171
0%
b1 *
1&
#172
0&
#173
b11 !
b11 .
1%
b0 *
1&
#174
0&
#175
0%
b1 *
1&
#176
0&
#177
b100 !
b100 .
1%
b0 *
1&
#178
0&
#179
0%
b1 *
1&
#180
0&
#181
b101 !
b101 .
1%
b0 *
1&
#182
0&
#183
0%
b1 *
1&
#184
0&
#185
b110 !
b110 .
1%
b0 *
1&
#186
0&
#187
0%
b1 *
1&
#188
0&
#189
b111 !
b111 .
1%
b0 *
1&
#190
0&
#191
0%
b1 *
1&
#192
0&
#193
b1000 !
b1000 .
1%
b0 *
1&
#194
0&
#195
0%
b1 *
1&
#196
0&
#197
b1001 !
b1001 .
1%
b0 *
1&
#198
0&
#199
0%
b1 *
1&
#200
0&
#201
b101 "
b101 ,
1#
b0 !
b0 .
1%
b0 *
1&
#202
0&
#203
0%
b1 *
1&
#204
0&
#205
0#
b1 !
b1 .
1%
b0 *
1&
#206
0&
#207
0%
b1 *
1&
#208
0&
#209
b10 !
b10 .
1%
b0 *
1&
#210
0&
#211
0%
b1 *
1&
#212
0&
#213
b11 !
b11 .
1%
b0 *
1&
#214
0&
#215
0%
b1 *
1&
#216
0&
#217
b100 !
b100 .
1%
b0 *
1&
#218
0&
#219
0%
b1 *
1&
#220
0&
#221
b101 !
b101 .
1%
b0 *
1&
#222
0&
#223
0%
b1 *
1&
#224
0&
#225
b110 !
b110 .
1%
b0 *
1&
#226
0&
#227
0%
b1 *
1&
#228
0&
#229
b111 !
b111 .
1%
b0 *
1&
#230
0&
#231
0%
b1 *
1&
#232
0&
#233
b1000 !
b1000 .
1%
b0 *
1&
#234
0&
#235
0%
b1 *
1&
#236
0&
#237
b1001 !
b1001 .
1%
b0 *
1&
#238
0&
#239
0%
b1 *
1&
#240
0&
#241
1$
b0 "
b0 ,
1#
b0 !
b0 .
1%
b0 *
1&
#242
0&
#243
0%
b1 *
1&
#244
0&
#245
0#
b1 !
b1 .
1%
b0 *
1&
#246
0&
#247
0%
b1 *
1&
#248
0&
#249
b10 !
b10 .
1%
b0 *
1&
#250
0&
#251
0%
b1 *
1&
#252
0&
#253
b11 !
b11 .
1%
b0 *
1&
#254
0&
#255
0%
b1 *
1&
#256
0&
#257
b100 !
b100 .
1%
b0 *
1&
#258
0&
#259
0%
b1 *
1&
#260
0&
#261
b101 !
b101 .
1%
b0 *
1&
#262
0&
#263
0%
b1 *
1&
#264
0&
#265
b110 !
b110 .
1%
b0 *
1&
#266
0&
#267
0%
b1 *
1&
#268
0&
#269
b111 !
b111 .
1%
b0 *
1&
#270
0&
#271
0%
b1 *
1&
#272
0&
#273
b1000 !
b1000 .
1%
b0 *
1&
#274
0&
#275
0%
b1 *
1&
#276
0&
#277
b1001 !
b1001 .
1%
b0 *
1&
#278
0&
#279
0%
b1 *
1&
#280
0&
#281
0$
b1 "
b1 ,
1#
b0 !
b0 .
1%
b0 *
1&
#282
0&
#283
0%
b1 *
1&
#284
0&
#285
0#
b1 !
b1 .
1%
b0 *
1&
#286
0&
#287
0%
b1 *
1&
#288
0&
#289
b10 !
b10 .
1%
b0 *
1&
#290
0&
#291
0%
b1 *
1&
#292
0&
#293
b11 !
b11 .
1%
b0 *
1&
#294
0&
#295
0%
b1 *
1&
#296
0&
#297
b100 !
b100 .
1%
b0 *
1&
#298
0&
#299
0%
b1 *
1&
#300
0&
#301
b101 !
b101 .
1%
b0 *
1&
#302
0&
#303
0%
b1 *
1&
#304
0&
#305
b110 !
b110 .
1%
b0 *
1&
#306
0&
#307
0%
b1 *
1&
#308
0&
#309
b111 !
b111 .
1%
b0 *
1&
#310
0&
#311
0%
b1 *
1&
#312
0&
#313
b1000 !
b1000 .
1%
b0 *
1&
#314
0&
#315
0%
b1 *
1&
#316
0&
#317
b1001 !
b1001 .
1%
b0 *
1&
#318
0&
#319
0%
b1 *
1&
#320
0&
#321
b10 "
b10 ,
1#
b0 !
b0 .
1%
b0 *
1&
#322
0&
#323
0%
b1 *
1&
#324
0&
#325
0#
b1 !
b1 .
1%
b0 *
1&
#326
0&
#327
0%
b1 *
1&
#328
0&
#329
b10 !
b10 .
1%
b0 *
1&
#330
0&
#331
0%
b1 *
1&
#332
0&
#333
b11 !
b11 .
1%
b0 *
1&
#334
0&
#335
0%
b1 *
1&
#336
0&
#337
b100 !
b100 .
1%
b0 *
1&
#338
0&
#339
0%
b1 *
1&
#340
0&
#341
b101 !
b101 .
1%
b0 *
1&
#342
0&
#343
0%
b1 *
1&
#344
0&
#345
b110 !
b110 .
1%
b0 *
1&
#346
0&
#347
0%
b1 *
1&
#348
0&
#349
b111 !
b111 .
1%
b0 *
1&
#350
0&
#351
0%
b1 *
1&
#352
0&
#353
b1000 !
b1000 .
1%
b0 *
1&
#354
0&
#355
0%
b1 *
1&
#356
0&
#357
b1001 !
b1001 .
1%
b0 *
1&
#358
0&
#359
0%
b1 *
1&
#360
0&
#361
b11 "
b11 ,
1#
b0 !
b0 .
1%
b0 *
1&
#362
0&
#363
0%
b1 *
1&
#364
0&
#365
0#
b1 !
b1 .
1%
b0 *
1&
#366
0&
#367
0%
b1 *
1&
#368
0&
#369
b10 !
b10 .
1%
b0 *
1&
#370
0&
#371
0%
b1 *
1&
#372
0&
#373
b11 !
b11 .
1%
b0 *
1&
#374
0&
#375
0%
b1 *
1&
#376
0&
#377
b100 !
b100 .
1%
b0 *
1&
#378
0&
#379
0%
b1 *
1&
#380
0&
#381
b101 !
b101 .
1%
b0 *
1&
#382
0&
#383
0%
b1 *
1&
#384
0&
#385
b110 !
b110 .
1%
b0 *
1&
#386
0&
#387
0%
b1 *
1&
#388
0&
#389
b111 !
b111 .
1%
b0 *
1&
#390
0&
#391
0%
b1 *
1&
#392
0&
#393
b1000 !
b1000 .
1%
b0 *
1&
#394
0&
#395
0%
b1 *
1&
#396
0&
#397
b1001 !
b1001 .
1%
b0 *
1&
#398
0&
#399
0%
b1 *
1&
#400
0&
#401
b100 "
b100 ,
1#
b0 !
b0 .
1%
b0 *
1&
