set.v
module setFSM #(
    parameter HOUR = 2'b00, MIN = 2'b01, SEC = 2'b10, DONE = 2'b11
) (
    input clk,
    input reset,
    input setbutton,
    input button1,
    input button2,
    output reg [1:0] hour1,
    output reg [3:0] hour2,
    output reg [2:0] min1,
    output reg [3:0] min2,
    output reg [2:0] sec1,
    output reg [3:0] sec2
);

    reg [1:0] state;
    reg isnext;
    reg isbutton1;
    reg isbutton2;

    // Synchronize inputs with the clock domain
    // reg nextbutton_sync, button1_sync, button2_sync;

    // always @(posedge clk or posedge reset) begin
    //     if (reset)
    //         nextbutton_sync <= 1'b0;
    //     else
    //         nextbutton_sync <= setbutton;
    // end

    // always @(posedge clk or posedge reset) begin
    //     if (reset)
    //         button1_sync <= 1'b0;
    //     else
    //         button1_sync <= button1;
    // end

    // always @(posedge clk or posedge reset) begin
    //     if (reset)
    //         button2_sync <= 1'b0;
    //     else
    //         button2_sync <= button2;
    // end

    // // Set isnext when setbutton is pressed
    // always @(posedge clk or posedge reset) begin
    //     if (reset)
    //         isnext <= 0;
    //     else if (nextbutton_sync)
    //         isnext <= 1;
    // end

    // // Set isbutton1 when button1 is pressed
    // always @(posedge clk or posedge reset) begin
    //     if (reset)
    //         isbutton1 <= 0;
    //     else if (button1_sync)
    //         isbutton1 <= 1;
    // end

    // // Set isbutton2 when button2 is pressed
    // always @(posedge clk or posedge reset) begin
    //     if (reset)
    //         isbutton2 <= 0;
    //     else if (button2_sync)
    //         isbutton2 <= 1;
    // end

    always @(posedge setbutton) begin
        isnext <= 1;
    end
    always @(posedge button1) begin
        isbutton1 <= 1;
    end
    always @(posedge button2) begin
        isbutton2 <= 1;
    end

    always @(posedge clk or posedge reset) begin
        if (reset) begin
            state <= HOUR;
            hour1 <= 2'b00;
            hour2 <= 4'b0000;
            min1 <= 3'b000;
            min2 <= 4'b0000;
            sec1 <= 3'b000;
            sec2 <= 4'b0000;
            isnext <= 0;
            isbutton1 <=0;
            isbutton2 <=0;
        end
        else begin
//Need to add overflow logic
            case (state)
                HOUR: begin
                    if (isbutton1) begin
                        hour1 <= (hour1 == 2'b11) ? 2'b00 : hour1 + 1;
                        isbutton1 <= 0;
                    end
                    if (isbutton2) begin
                        hour2 <= (hour2 == 4'b1010) ? 4'b0000 : hour2 + 1;
                        isbutton2 <= 0;
                    end
                    state <= isnext ? MIN : HOUR;
                    isnext <=0;
                end

                MIN: begin
                    if (isbutton1) begin
                        min1 <= (min1 == 3'b110) ? 3'b000 : min1 + 1;
                        isbutton1 <= 0;
                    end
                    if (isbutton2) begin
                        min2 <= (min2 == 4'b1010) ? 4'b0000 : min2 + 1;
                        isbutton2 <= 0;
                    end
                    state <= isnext ? SEC : MIN;
                    isnext <= 0;
                end

                SEC: begin
                    if (isbutton1) begin
                        sec1 <= (sec1 == 3'b110) ? 3'b000 : sec1 + 1;
                        isbutton1 <= 0;
                    end
                    if (isbutton2) begin
                        sec2 <= (sec2 == 4'b1010) ? 4'b0000 : sec2 + 1;
                        isbutton2 <= 0;
                    end
                    state <= isnext ? DONE : SEC;
                    isnext <= 0;
                end
                
                DONE: begin
                    
                end

                default: state <= HOUR;
            endcase
        end
    end
endmodule

bcdcounter.v

// count till max_count

module bcd_counter#(
    parameter MAX_COUNT = 4'd9
) (
    input trigger,
    input rst,
    input set,
    input wire[3:0] set_value,
    output reg[3:0] counter,
    output reg overflow
);

    always @ (rst) begin : BCD_CRST
        counter <= 0;
        overflow <= 0;
    end

    always @ (posedge trigger, set_value) begin : BCD_COUNT
        if(set) begin
            counter <= set_value;
            overflow <= 0;
        end
        else if(counter < MAX_COUNT) begin
            counter = counter + 1;
            overflow <= 0;
        end
        else if(counter >= MAX_COUNT) begin
            counter = 0;
            overflow <= 1;
        end
    end

endmodule

// converts a binary number from 0...23 into bcd values
// fast as fuck
module bin_to_bcd(input wire[4:0] binary, output wire[1:0] d1, output wire[3:0] d0);
    wire[8:0] bin9;
    wire[8:0] q;
    assign bin9[8:0] = {4'b0, binary[4:0]};
    assign q[8:0] = (bin9 + (bin9 << 2) + (bin9 << 3));
    assign d1[1:0] = q[8:7];
    assign d0[3:0] = binary + {q[7], q[8], q[7] | q[8], q[7], 1'b0};
endmodule

module bcd_to_bin(input wire[3:0] d1, input wire[3:0] d0, output wire[4:0] binary);
    assign binary = d0 + (d1 << 1) + (d1 << 3);
endmodule

module hour_counter
(
    input trigger,
    input rst,
    input set,
    input mode_12h,
    input wire[3:0] set_h0,
    input wire[3:0] set_h1,
    input wire set_am_pm,
    output wire[3:0] h0,
    output wire[1:0] h1,
    output wire am_pm,
    output reg overflow
);

    wire[4:0] set_hr;
    reg[4:0] hr_counter = 0;

    wire[4:0] hr_mode;
    assign am_pm = hr_counter > 11;
    assign hr_mode = hr_counter + {mode_12h & am_pm, 1'b0, mode_12h & am_pm, 2'b0};

    always @ (rst) begin : BCD_CRST
        hr_counter <= 0;
        overflow <= 0;
    end

    bin_to_bcd binToBCD(.binary(hr_mode), .d1(h1), .d0(h0));
    bcd_to_bin bcdToBinSET(.d1(set_h1), .d0(set_h0), .binary(set_hr));

    always @ (posedge trigger, set_hr) begin : BCD_COUNT
        if(set == 1) begin
        hr_counter <= set_hr + {1'b0, mode_12h & set_am_pm, mode_12h & set_am_pm, 2'b0}; // set_am_pm
        overflow <= 0;
        end
        else if(hr_counter < 23) begin
            hr_counter = hr_counter + 1;
            overflow <= 0;
        end
        else begin
            hr_counter <= 0;
            overflow <= 1;
        end
    end

endmodule

module sclk #(parameter F_MINUS1 = 10) (input clk, input rst, output reg sec_clk);

    reg[31:0] counter;

    always @ (posedge clk) begin
        if(rst) begin
            counter <= 0;
            sec_clk <= 0;
        end
        else if(counter < F_MINUS1) begin
            counter <= counter + 1;
            sec_clk <= 0;
        end
        else if(counter >= F_MINUS1) begin
            counter <= 0;
            sec_clk <= 1;
        end
    end

endmodule

// h1 h2 : m1 m2 : s1 s2
// 1 + 4 + 3 + 4 + 3 + 4
// 19

module time_view
(
    input clk, 
    input rst,
    input mode12h,
    input set_time,
    input set_alarm,
    input button1,
    input button2,
    input wire[1:0] alarm_id,
    input wire[19:0] stime_alarm,
    input wire sam_pm,
    output wire[19:0] hh_mm_ss,
    output wire am_pm
);

    wire sec_clk;
    wire bcd_clk[6];
    wire wireX[2];
    wire[19:0] stime;

    // clk frequency is 2 Hz
    sclk #(1) second_clk(.clk(clk), .rst(rst), .sec_clk(sec_clk));

    bcd_counter #(9) s0(.trigger(sec_clk),    .rst(rst), .set(set_time), .set_value(stime[3:0]), .counter(hh_mm_ss[3:0]), .overflow(bcd_clk[0]));
    bcd_counter #(5) s1(.trigger(bcd_clk[0]), .rst(rst), .set(set_time), .set_value({1'b0, stime[6:4]}), .counter({wireX[0], hh_mm_ss[6:4]}), .overflow(bcd_clk[1]));

    bcd_counter #(9) m0(.trigger(bcd_clk[1]), .rst(rst), .set(set_time), .set_value(stime[10: 7]), .counter(hh_mm_ss[10: 7]), .overflow(bcd_clk[2]));
    bcd_counter #(5) m1(.trigger(bcd_clk[2]), .rst(rst), .set(set_time), .set_value({1'b0, stime[13:11]}), .counter({wireX[1], hh_mm_ss[13:11]}), .overflow(bcd_clk[3]));

    hour_counter hrc(.trigger(bcd_clk[3]), .rst(rst), .set(set_time), .mode_12h(mode12h),
                           .set_h0(stime[17:14]), .set_h1({1'b0, 1'b0, stime[19:18]}), .set_am_pm(sam_pm),
                           .h0(hh_mm_ss[17:14]), .h1(hh_mm_ss[19:18]), .am_pm(am_pm), .overflow(bcd_clk[4]));
    
    setFSM setlogic(.clk(clk), .reset(rst), .setbutton(sam_pm), .button1(button1), .button2(button2), .hour1(stime[19:18]), .hour2(stime[17:14]), .min1(stime[13:11]), .min2(stime[10:7]), .sec1(stime[6:4]), .sec2(stime[3:0]));

//    always @ (posedge clk) begin
//        if(rst) begin
//            // reset all state
//            ;
//        end
//    end

endmodule

duttb.v
module time_view_tb();

    reg clk, rst, mode12h, set_time, set_alarm, button1, button2, sam_pm;
    reg [1:0] alarm_id;
    reg [19:0] stime_alarm;
    wire [19:0] hh_mm_ss;
    wire am_pm;

    // Instantiate the time_view module
    time_view dut(
        .clk(clk),
        .rst(rst),
        .mode12h(mode12h),
        .set_time(set_time),
        .set_alarm(set_alarm),
        .button1(button1),
        .button2(button2),
        .alarm_id(alarm_id),
        .stime_alarm(stime_alarm),
        .sam_pm(sam_pm),
        .hh_mm_ss(hh_mm_ss),
        .am_pm(am_pm)
    );

    // Clock generation
    always #5 clk = ~clk;

    // Reset generation
    initial begin
        $dumpfile("tb.vcd");
        $dumpvars;

        // Initial state setup
        clk = 0;
        rst = 1;
        mode12h = 1'b0;
        set_time = 1'b0;
        set_alarm = 1'b0;
        button1 = 1'b0;
        button2 = 1'b0;
        sam_pm = 1'b0;
        alarm_id = 2'b00;
        stime_alarm = 20'b0;

        // Release reset after some time
        #10 rst = 0;
        #100;

        // Test case 1: Set time mode, set hours to 12, minutes to 34, seconds to 56, AM
        set_time = 1'b1;
        #100;
        repeat(12) begin
            #50 button1 = 1'b1; // Press button 1
            #50 button1 = 1'b0; // Release button 1
            #50 button2 = 1'b1; // Press button 2
            #50 button2 = 1'b0; // Release button 2
        end

        sam_pm = 1;
        #100;
        repeat(12) begin
            #50 button1 = 1'b1; // Press button 1
            #50 button1 = 1'b0; // Release button 1
            #50 button2 = 1'b1; // Press button 2
            #50 button2 = 1'b0; // Release button 2
        end

        sam_pm = 0;
        #100;

        repeat(12) begin
            #50 button1 = 1'b1; // Press button 1
            #50 button2 = 1'b1; // Press button 2
            #50 button1 = 1'b0; // Release button 1
            #50 button2 = 1'b0; // Release button 2
        end

        sam_pm = 1;

        // Test case 2: Change to PM
        #100;
        set_time = 0;
        sam_pm = 1'b0;

        // Test case 4: Press button 2 to increment minutes
        #100;
        button1 = 1'b0;
        #50 button2 = 1'b1; // Press button 2
        #50 button2 = 1'b0; // Release button 2

        // Test case 6: Toggle mode 12h to 24h
        #100;
        mode12h = 1'b1;
        
        // Add more test cases as needed

        // Finish simulation
        #1000;
        $finish;
    end

endmodule

tb.vcd
$date
	Wed May  1 03:02:14 2024
$end
$version
	Icarus Verilog
$end
$timescale
	1s
$end
$scope module time_view_tb $end
$var wire 20 ! hh_mm_ss [19:0] $end
$var wire 1 " am_pm $end
$var reg 2 # alarm_id [1:0] $end
$var reg 1 $ button1 $end
$var reg 1 % button2 $end
$var reg 1 & clk $end
$var reg 1 ' mode12h $end
$var reg 1 ( rst $end
$var reg 1 ) sam_pm $end
$var reg 1 * set_alarm $end
$var reg 1 + set_time $end
$var reg 20 , stime_alarm [19:0] $end
$scope module dut $end
$var wire 2 - alarm_id [1:0] $end
$var wire 1 $ button1 $end
$var wire 1 % button2 $end
$var wire 1 & clk $end
$var wire 1 ' mode12h $end
$var wire 1 ( rst $end
$var wire 1 ) sam_pm $end
$var wire 1 * set_alarm $end
$var wire 1 + set_time $end
$var wire 20 . stime_alarm [19:0] $end
$var wire 20 / stime [19:0] $end
$var wire 1 0 sec_clk $end
$var wire 20 1 hh_mm_ss [19:0] $end
$var wire 1 " am_pm $end
$scope module hrc $end
$var wire 1 ' mode_12h $end
$var wire 1 ( rst $end
$var wire 1 + set $end
$var wire 1 ) set_am_pm $end
$var wire 4 2 set_h0 [3:0] $end
$var wire 4 3 set_h1 [3:0] $end
$var wire 1 4 trigger $end
$var wire 5 5 set_hr [4:0] $end
$var wire 5 6 hr_mode [4:0] $end
$var wire 2 7 h1 [1:0] $end
$var wire 4 8 h0 [3:0] $end
$var wire 1 " am_pm $end
$var reg 5 9 hr_counter [4:0] $end
$var reg 1 : overflow $end
$scope module bcdToBinSET $end
$var wire 4 ; d0 [3:0] $end
$var wire 4 < d1 [3:0] $end
$var wire 5 = binary [4:0] $end
$upscope $end
$scope module binToBCD $end
$var wire 5 > binary [4:0] $end
$var wire 9 ? q [8:0] $end
$var wire 2 @ d1 [1:0] $end
$var wire 4 A d0 [3:0] $end
$var wire 9 B bin9 [8:0] $end
$upscope $end
$scope begin BCD_COUNT $end
$upscope $end
$scope begin BCD_CRST $end
$upscope $end
$upscope $end
$scope module m0 $end
$var wire 1 ( rst $end
$var wire 1 + set $end
$var wire 4 C set_value [3:0] $end
$var wire 1 D trigger $end
$var reg 4 E counter [3:0] $end
$var reg 1 F overflow $end
$scope begin BCD_COUNT $end
$upscope $end
$scope begin BCD_CRST $end
$upscope $end
$upscope $end
$scope module m1 $end
$var wire 1 ( rst $end
$var wire 1 + set $end
$var wire 4 G set_value [3:0] $end
$var wire 1 F trigger $end
$var reg 4 H counter [3:0] $end
$var reg 1 4 overflow $end
$scope begin BCD_COUNT $end
$upscope $end
$scope begin BCD_CRST $end
$upscope $end
$upscope $end
$scope module s0 $end
$var wire 1 ( rst $end
$var wire 1 + set $end
$var wire 4 I set_value [3:0] $end
$var wire 1 0 trigger $end
$var reg 4 J counter [3:0] $end
$var reg 1 K overflow $end
$scope begin BCD_COUNT $end
$upscope $end
$scope begin BCD_CRST $end
$upscope $end
$upscope $end
$scope module s1 $end
$var wire 1 ( rst $end
$var wire 1 + set $end
$var wire 4 L set_value [3:0] $end
$var wire 1 K trigger $end
$var reg 4 M counter [3:0] $end
$var reg 1 D overflow $end
$scope begin BCD_COUNT $end
$upscope $end
$scope begin BCD_CRST $end
$upscope $end
$upscope $end
$scope module second_clk $end
$var wire 1 & clk $end
$var wire 1 ( rst $end
$var reg 32 N counter [31:0] $end
$var reg 1 0 sec_clk $end
$upscope $end
$scope module setlogic $end
$var wire 1 $ button1 $end
$var wire 1 % button2 $end
$var wire 1 & clk $end
$var wire 1 ( reset $end
$var wire 1 ) setbutton $end
$var reg 2 O hour1 [1:0] $end
$var reg 4 P hour2 [3:0] $end
$var reg 1 Q isbutton1 $end
$var reg 1 R isbutton2 $end
$var reg 1 S isnext $end
$var reg 3 T min1 [2:0] $end
$var reg 4 U min2 [3:0] $end
$var reg 3 V sec1 [2:0] $end
$var reg 4 W sec2 [3:0] $end
$var reg 2 X state [1:0] $end
$upscope $end
$upscope $end
$upscope $end
$enddefinitions $end
#0
$dumpvars
b0 X
b0 W
b0 V
b0 U
b0 T
0S
0R
0Q
b0 P
b0 O
bx N
b1 M
b0 L
0K
b1 J
b0 I
b1 H
b0 G
0F
b1 E
0D
b0 C
b1 B
b1 A
b0 @
b1101 ?
b1 >
b0 =
b0 <
b0 ;
0:
b1 9
b1 8
b0 7
b1 6
b0 5
04
b0 3
b0 2
b100100010010001 1
x0
b0 /
b0 .
b0 -
b0 ,
0+
0*
0)
1(
0'
0&
0%
0$
b0 #
0"
b100100010010001 !
$end
#5
00
b0 N
1&
#10
b0 8
b0 A
b0 J
b0 M
b0 !
b0 1
b0 E
b0 H
b0 ?
b0 B
b0 6
b0 >
b0 9
0&
0(
#15
b1 N
1&
#20
0&
#25
b1 !
b1 1
b1 J
10
b0 N
1&
#30
0&
#35
00
b1 N
1&
#40
0&
#45
b10 !
b10 1
b10 J
10
b0 N
1&
#50
0&
#55
00
b1 N
1&
#60
0&
#65
b11 !
b11 1
b11 J
10
b0 N
1&
#70
0&
#75
00
b1 N
1&
#80
0&
#85
b100 !
b100 1
b100 J
10
b0 N
1&
#90
0&
#95
00
b1 N
1&
#100
0&
#105
b101 !
b101 1
b101 J
10
b0 N
1&
#110
0&
1+
#115
00
b1 N
1&
#120
0&
#125
b0 !
b0 1
b0 J
10
b0 N
1&
#130
0&
#135
00
b1 N
1&
#140
0&
#145
10
b0 N
1&
#150
0&
#155
00
b1 N
1&
#160
0&
#165
10
b0 N
1&
#170
0&
#175
00
b1 N
1&
#180
0&
#185
10
b0 N
1&
#190
0&
#195
00
b1 N
1&
#200
0&
#205
10
b0 N
1&
#210
0&
#215
00
b1 N
1&
#220
0&
#225
10
b0 N
1&
#230
0&
#235
00
b1 N
1&
#240
0&
#245
10
b0 N
1&
#250
0&
#255
00
b1 N
1&
#260
1Q
0&
1$
#265
b1 7
b1 @
b1000000000000000000 !
b1000000000000000000 1
b0 8
b0 A
b10000010 ?
b1010 B
b1010 6
b1010 >
b1010 9
b1010 5
b1010 =
b1 3
b1 <
10
b0 N
0Q
b1000000000000000000 /
b1 O
1&
#270
0&
#275
00
b1 N
1&
#280
0&
#285
10
b0 N
1&
#290
0&
#295
00
b1 N
1&
#300
0&
#305
10
b0 N
1&
#310
0&
0$
#315
00
b1 N
1&
#320
0&
#325
10
b0 N
1&
#330
0&
#335
00
b1 N
1&
#340
0&
#345
10
b0 N
1&
#350
0&
#355
00
b1 N
1&
#360
1R
0&
1%
#365
b1000100000000000000 !
b1000100000000000000 1
b1 8
b1 A
b10001111 ?
b1011 B
b1011 6
b1011 >
b1011 9
b1011 5
b1011 =
b1 2
b1 ;
10
b0 N
0R
b1000100000000000000 /
b1 P
1&
#370
0&
#375
00
b1 N
1&
#380
0&
#385
10
b0 N
1&
#390
0&
#395
00
b1 N
1&
#400
0&
#405
10
b0 N
1&
#410
0&
0%
#415
00
b1 N
1&
#420
0&
#425
10
b0 N
1&
#430
0&
#435
00
b1 N
1&
#440
0&
#445
10
b0 N
1&
#450
0&
#455
00
b1 N
1&
#460
1Q
0&
1$
#465
b10 7
b10 @
b10000100000000000000 !
b10000100000000000000 1
b1 8
b1 A
1"
b100010001 ?
b10101 B
b10101 6
b10101 >
b10101 9
b10101 5
b10101 =
b10 3
b10 <
10
b0 N
0Q
b10000100000000000000 /
b10 O
1&
#470
0&
#475
00
b1 N
1&
#480
0&
#485
10
b0 N
1&
#490
0&
#495
00
b1 N
1&
#500
0&
#505
10
b0 N
1&
#510
0&
0$
#515
00
b1 N
1&
#520
0&
#525
10
b0 N
1&
#530
0&
#535
00
b1 N
1&
#540
0&
#545
10
b0 N
1&
#550
0&
#555
00
b1 N
1&
#560
1R
0&
1%
#565
b10001000000000000000 !
b10001000000000000000 1
b10 8
b10 A
b100011110 ?
b10110 B
b10110 6
b10110 >
b10110 9
b10110 5
b10110 =
b10 2
b10 ;
10
b0 N
0R
b10001000000000000000 /
b10 P
1&
#570
0&
#575
00
b1 N
1&
#580
0&
#585
10
b0 N
1&
#590
0&
#595
00
b1 N
1&
#600
0&
#605
10
b0 N
1&
#610
0&
0%
#615
00
b1 N
1&
#620
0&
#625
10
b0 N
1&
#630
0&
#635
00
b1 N
1&
#640
0&
#645
10
b0 N
1&
#650
0&
#655
00
b1 N
1&
#660
1Q
0&
1$
#665
b0 7
b0 @
b0 !
b0 1
b0 8
b0 A
0"
b0 ?
b0 B
b0 6
b0 >
b0 9
b0 5
b0 =
b11 3
b11 <
10
b0 N
0Q
b11001000000000000000 /
b11 O
1&
#670
0&
#675
00
b1 N
1&
#680
0&
#685
10
b0 N
1&
#690
0&
#695
00
b1 N
1&
#700
0&
#705
10
b0 N
1&
#710
0&
0$
#715
00
b1 N
1&
#720
0&
#725
10
b0 N
1&
#730
0&
#735
00
b1 N
1&
#740
0&
#745
10
b0 N
1&
#750
0&
#755
00
b1 N
1&
#760
1R
0&
1%
#765
b100000000000000 !
b100000000000000 1
b1 8
b1 A
b1101 ?
b1 B
b1 6
b1 >
b1 9
b1 5
b1 =
b11 2
b11 ;
10
b0 N
0R
b11001100000000000000 /
b11 P
1&
#770
0&
#775
00
b1 N
1&
#780
0&
#785
10
b0 N
1&
#790
0&
#795
00
b1 N
1&
#800
0&
#805
10
b0 N
1&
#810
0&
0%
#815
00
b1 N
1&
#820
0&
#825
10
b0 N
1&
#830
0&
#835
00
b1 N
1&
#840
0&
#845
10
b0 N
1&
#850
0&
#855
00
b1 N
1&
#860
1Q
0&
1$
#865
b1100000000000000 !
b1100000000000000 1
b11 8
b11 A
b100111 ?
b11 B
b11 6
b11 >
b11 9
b11 5
b11 =
b0 3
b0 <
10
b0 N
0Q
b1100000000000000 /
b0 O
1&
#870
0&
#875
00
b1 N
1&
#880
0&
#885
10
b0 N
1&
#890
0&
#895
00
b1 N
1&
#900
0&
#905
10
b0 N
1&
#910
0&
0$
#915
00
b1 N
1&
#920
0&
#925
10
b0 N
1&
#930
0&
#935
00
b1 N
1&
#940
0&
#945
10
b0 N
1&
#950
0&
#955
00
b1 N
1&
#960
1R
0&
1%
#965
b10000000000000000 !
b10000000000000000 1
b100 8
b100 A
b110100 ?
b100 B
b100 6
b100 >
b100 9
b100 5
b100 =
b100 2
b100 ;
10
b0 N
0R
b10000000000000000 /
b100 P
1&
#970
0&
#975
00
b1 N
1&
#980
0&
#985
10
b0 N
1&
#990
0&
#995
00
b1 N
1&
#1000
0&
#1005
10
b0 N
1&
#1010
0&
0%
#1015
00
b1 N
1&
#1020
0&
#1025
10
b0 N
1&
#1030
0&
#1035
00
b1 N
1&
#1040
0&
#1045
10
b0 N
1&
#1050
0&
#1055
00
b1 N
1&
#1060
1Q
0&
1$
#1065
b1 7
b1 @
b1010000000000000000 !
b1010000000000000000 1
b100 8
b100 A
1"
b10110110 ?
b1110 B
b1110 6
b1110 >
b1110 9
b1110 5
b1110 =
b1 3
b1 <
10
b0 N
0Q
b1010000000000000000 /
b1 O
1&
#1070
0&
#1075
00
b1 N
1&
#1080
0&
#1085
10
b0 N
1&
#1090
0&
#1095
00
b1 N
1&
#1100
0&
#1105
10
b0 N
1&
#1110
0&
0$
#1115
00
b1 N
1&
#1120
0&
#1125
10
b0 N
1&
#1130
0&
#1135
00
b1 N
1&
#1140
0&
#1145
10
b0 N
1&
#1150
0&
#1155
00
b1 N
1&
#1160
1R
0&
1%
#1165
b1010100000000000000 !
b1010100000000000000 1
b101 8
b101 A
b11000011 ?
b1111 B
b1111 6
b1111 >
b1111 9
b1111 5
b1111 =
b101 2
b101 ;
10
b0 N
0R
b1010100000000000000 /
b101 P
1&
#1170
0&
#1175
00
b1 N
1&
#1180
0&
#1185
10
b0 N
1&
#1190
0&
#1195
00
b1 N
1&
#1200
0&
#1205
10
b0 N
1&
#1210
0&
0%
#1215
00
b1 N
1&
#1220
0&
#1225
10
b0 N
1&
#1230
0&
#1235
00
b1 N
1&
#1240
0&
#1245
10
b0 N
1&
#1250
0&
#1255
00
b1 N
1&
#1260
1Q
0&
1$
#1265
b10 7
b10 @
b10010100000000000000 !
b10010100000000000000 1
b101 8
b101 A
b101000101 ?
b11001 B
b11001 6
b11001 >
b11001 9
b11001 5
b11001 =
b10 3
b10 <
10
b0 N
0Q
b10010100000000000000 /
b10 O
1&
#1270
0&
#1275
00
b1 N
1&
#1280
0&
#1285
10
b0 N
1&
#1290
0&
#1295
00
b1 N
1&
#1300
0&
#1305
10
b0 N
1&
#1310
0&
0$
#1315
00
b1 N
1&
#1320
0&
#1325
10
b0 N
1&
#1330
0&
#1335
00
b1 N
1&
#1340
0&
#1345
10
b0 N
1&
#1350
0&
#1355
00
b1 N
1&
#1360
1R
0&
1%
#1365
b10011000000000000000 !
b10011000000000000000 1
b110 8
b110 A
b101010010 ?
b11010 B
b11010 6
b11010 >
b11010 9
b11010 5
b11010 =
b110 2
b110 ;
10
b0 N
0R
b10011000000000000000 /
b110 P
1&
#1370
0&
#1375
00
b1 N
1&
#1380
0&
#1385
10
b0 N
1&
#1390
0&
#1395
00
b1 N
1&
#1400
0&
#1405
10
b0 N
1&
#1410
0&
0%
#1415
00
b1 N
1&
#1420
0&
#1425
10
b0 N
1&
#1430
0&
#1435
00
b1 N
1&
#1440
0&
#1445
10
b0 N
1&
#1450
0&
#1455
00
b1 N
1&
#1460
1Q
0&
1$
#1465
b0 7
b0 @
b10000000000000000 !
b10000000000000000 1
b100 8
b100 A
0"
b110100 ?
b100 B
b100 6
b100 >
b100 9
b100 5
b100 =
b11 3
b11 <
10
b0 N
0Q
b11011000000000000000 /
b11 O
1&
#1470
0&
#1475
00
b1 N
1&
#1480
0&
#1485
10
b0 N
1&
#1490
0&
#1495
00
b1 N
1&
#1500
0&
#1505
10
b0 N
1&
#1510
0&
0$
#1515
00
b1 N
1&
#1520
0&
#1525
10
b0 N
1&
#1530
0&
#1535
00
b1 N
1&
#1540
0&
#1545
10
b0 N
1&
#1550
0&
#1555
00
b1 N
1&
#1560
1R
0&
1%
#1565
b10100000000000000 !
b10100000000000000 1
b101 8
b101 A
b1000001 ?
b101 B
b101 6
b101 >
b101 9
b101 5
b101 =
b111 2
b111 ;
10
b0 N
0R
b11011100000000000000 /
b111 P
1&
#1570
0&
#1575
00
b1 N
1&
#1580
0&
#1585
10
b0 N
1&
#1590
0&
#1595
00
b1 N
1&
#1600
0&
#1605
10
b0 N
1&
#1610
0&
0%
#1615
00
b1 N
1&
#1620
0&
#1625
10
b0 N
1&
#1630
0&
#1635
00
b1 N
1&
#1640
0&
#1645
10
b0 N
1&
#1650
0&
#1655
00
b1 N
1&
#1660
1Q
0&
1$
#1665
b11100000000000000 !
b11100000000000000 1
b111 8
b111 A
b1011011 ?
b111 B
b111 6
b111 >
b111 9
b111 5
b111 =
b0 3
b0 <
10
b0 N
0Q
b11100000000000000 /
b0 O
1&
#1670
0&
#1675
00
b1 N
1&
#1680
0&
#1685
10
b0 N
1&
#1690
0&
#1695
00
b1 N
1&
#1700
0&
#1705
10
b0 N
1&
#1710
0&
0$
#1715
00
b1 N
1&
#1720
0&
#1725
10
b0 N
1&
#1730
0&
#1735
00
b1 N
1&
#1740
0&
#1745
10
b0 N
1&
#1750
0&
#1755
00
b1 N
1&
#1760
1R
0&
1%
#1765
b100000000000000000 !
b100000000000000000 1
b1000 8
b1000 A
b1101000 ?
b1000 B
b1000 6
b1000 >
b1000 9
b1000 5
b1000 =
b1000 2
b1000 ;
10
b0 N
0R
b100000000000000000 /
b1000 P
1&
#1770
0&
#1775
00
b1 N
1&
#1780
0&
#1785
10
b0 N
1&
#1790
0&
#1795
00
b1 N
1&
#1800
0&
#1805
10
b0 N
1&
#1810
0&
0%
#1815
00
b1 N
1&
#1820
0&
#1825
10
b0 N
1&
#1830
0&
#1835
00
b1 N
1&
#1840
0&
#1845
10
b0 N
1&
#1850
0&
#1855
00
b1 N
1&
#1860
1Q
0&
1$
#1865
b1 7
b1 @
b1100000000000000000 !
b1100000000000000000 1
b1000 8
b1000 A
1"
b11101010 ?
b10010 B
b10010 6
b10010 >
b10010 9
b10010 5
b10010 =
b1 3
b1 <
10
b0 N
0Q
b1100000000000000000 /
b1 O
1&
#1870
0&
#1875
00
b1 N
1&
#1880
0&
#1885
10
b0 N
1&
#1890
0&
#1895
00
b1 N
1&
#1900
0&
#1905
10
b0 N
1&
#1910
0&
0$
#1915
00
b1 N
1&
#1920
0&
#1925
10
b0 N
1&
#1930
0&
#1935
00
b1 N
1&
#1940
0&
#1945
10
b0 N
1&
#1950
0&
#1955
00
b1 N
1&
#1960
1R
0&
1%
#1965
b1100100000000000000 !
b1100100000000000000 1
b1001 8
b1001 A
b11110111 ?
b10011 B
b10011 6
b10011 >
b10011 9
b10011 5
b10011 =
b1001 2
b1001 ;
10
b0 N
0R
b1100100000000000000 /
b1001 P
1&
#1970
0&
#1975
00
b1 N
1&
#1980
0&
#1985
10
b0 N
1&
#1990
0&
#1995
00
b1 N
1&
#2000
0&
#2005
10
b0 N
1&
#2010
0&
0%
#2015
00
b1 N
1&
#2020
0&
#2025
10
b0 N
1&
#2030
0&
#2035
00
b1 N
1&
#2040
0&
#2045
10
b0 N
1&
#2050
0&
#2055
00
b1 N
1&
#2060
1Q
0&
1$
#2065
b10 7
b10 @
b10100100000000000000 !
b10100100000000000000 1
b1001 8
b1001 A
b101111001 ?
b11101 B
b11101 6
b11101 >
b11101 9
b11101 5
b11101 =
b10 3
b10 <
10
b0 N
0Q
b10100100000000000000 /
b10 O
1&
#2070
0&
#2075
00
b1 N
1&
#2080
0&
#2085
10
b0 N
1&
#2090
0&
#2095
00
b1 N
1&
#2100
0&
#2105
10
b0 N
1&
#2110
0&
0$
#2115
00
b1 N
1&
#2120
0&
#2125
10
b0 N
1&
#2130
0&
#2135
00
b1 N
1&
#2140
0&
#2145
10
b0 N
1&
#2150
0&
#2155
00
b1 N
1&
#2160
1R
0&
1%
#2165
b11 7
b11 @
b11110000000000000000 !
b11110000000000000000 1
b1100 8
b1100 A
b110000110 ?
b11110 B
b11110 6
b11110 >
b11110 9
b11110 5
b11110 =
b1010 2
b1010 ;
10
b0 N
0R
b10101000000000000000 /
b1010 P
1&
#2170
0&
#2175
00
b1 N
1&
#2180
0&
#2185
10
b0 N
1&
#2190
0&
#2195
00
b1 N
1&
#2200
0&
#2205
10
b0 N
1&
#2210
0&
0%
#2215
00
b1 N
1&
#2220
0&
#2225
10
b0 N
1&
#2230
0&
#2235
00
b1 N
1&
#2240
0&
#2245
10
b0 N
1&
#2250
0&
#2255
00
b1 N
1&
#2260
1Q
0&
1$
#2265
b0 7
b0 @
b100000000000000000 !
b100000000000000000 1
b1000 8
b1000 A
0"
b1101000 ?
b1000 B
b1000 6
b1000 >
b1000 9
b1000 5
b1000 =
b11 3
b11 <
10
b0 N
0Q
b11101000000000000000 /
b11 O
1&
#2270
0&
#2275
00
b1 N
1&
#2280
0&
#2285
10
b0 N
1&
#2290
0&
#2295
00
b1 N
1&
#2300
0&
#2305
10
b0 N
1&
#2310
0&
0$
#2315
00
b1 N
1&
#2320
0&
#2325
10
b0 N
1&
#2330
0&
#2335
00
b1 N
1&
#2340
0&
#2345
10
b0 N
1&
#2350
0&
#2355
00
b1 N
1&
#2360
1R
0&
1%
#2365
b11 7
b11 @
b11110000000000000000 !
b11110000000000000000 1
b1100 8
b1100 A
1"
b110000110 ?
b11110 B
b11110 6
b11110 >
b11110 9
b11110 5
b11110 =
b0 2
b0 ;
10
b0 N
0R
b11000000000000000000 /
b0 P
1&
#2370
0&
#2375
00
b1 N
1&
#2380
0&
#2385
10
b0 N
1&
#2390
0&
#2395
00
b1 N
1&
#2400
0&
#2405
10
b0 N
1&
