features/date.v

module datemodule(input clk, input [7:0] hour_in, input [23:0] date_in, input [1:0] date_mode, output [23:0] date_out);

  //Time signal format: hhhh_hhhh
  //Date signal format: dddd_dddd.mmmm_mmmm.0010_0000_yyyy_yyyy   (1-1-2000 --> 12-12-2099) *CAUTION ABOUT THE 20** FORMAT OF YEAR*
  //When date_mode is 2, date_in is set
  //Date transitions delay is one clock cycle (posedge (hour_in = 23) --> posedge (hour_in = 0) --> posedge (date_out is changed))
  //clk: mclk, hour_in: bufferofhour, date_in: bufferofdate, date_mode: clk_mode, date_out: date
  //need to implement set logic for dates

  //separated date signals to respective meaning
  wire [7:0] day_in;
  wire [7:0] month_in;
  wire [7:0] year_in;

  reg [7:0] day_reg, day_reg_del; //day_reg_del: delayed signal
  reg [7:0] month_reg, month_reg_del; //month_reg_del: delayed signal
  reg [7:0] year_reg;

  reg [7:0] hour_reg; //Store previous hour data
  reg new_day; //Detect new day
  wire new_year, new_month; //Detect new year/month

  //separation and combination of date signals
  assign {day_in, month_in, year_in} = date_in;
  assign date_out = {day_reg, month_reg, year_reg};

  //edge detaction for year & month changes
  assign new_year = (month_reg == 8'h01) & (month_reg_del != 8'h01);
  assign new_month = (day_reg == 8'h01) & (day_reg_del != 8'h01);

  always@(posedge clk) //edge detection
    begin
      new_day <= (hour_in == 8'h0) & (hour_reg == 8'h23);
    end

  always@(posedge clk) //generate delayed signals for edge detection
    begin
      hour_reg <= hour_in;
      day_reg_del <= day_reg;
      month_reg_del <= month_reg;
    end

  //handle year
  always@(posedge clk or posedge date_mode)
    begin
      if(date_mode == 2'b10)  //clk_mode == 2 for set date
        begin
          year_reg <= year_in;
        end
      else
        begin
          if(new_year)
            begin
              casex(year_reg)
                8'h?9: year_reg <= {(year_reg[7:4]+4'h1),4'h0}; //(2009 --> 2010)
                default: year_reg <= year_reg + 8'b01; //(2008 --> 2009)
              endcase 
            end
        end
    end     

  //handle month
  always@(posedge clk or posedge date_mode)
    begin
      if (date_mode == 2'b10) 
        begin
          month_reg <= month_in;
        end
      else
        begin
          if(new_month)
            begin
              case(month_reg)
                8'h12: month_reg <= 8'h01; //(Dec --> Jan)
                8'h09: month_reg <= 8'h10; //(Sept --> Oct)
                default: month_reg <= month_reg + 4'h1;
              endcase 
            end
        end
    end     
    
  //handle day
  always@(posedge clk or posedge date_mode) 
    begin
      if(date_mode == 2'b10)  //clk_mode == 2 for set date
        begin
          day_reg <= day_in;
        end
      else
        begin
          if(new_day)
            begin
              casex(month_reg)
                5'd2: //February
                    casex(day_reg)
                      8'h29: day_reg <= 8'h01; //(Feb 29 --> Feb 1)
                      8'h28: day_reg <= (year_reg[1:0] == 2'b00) ? 8'h29 : 8'h1; //Leap year (only divisibility by 4 check), enough for 2000-2099
                      8'h?9: day_reg <= {(day_reg[5:4]+2'h1),4'h0}; //(Feb 09 --> Feb 10)
                      default: day_reg <= day_reg + 8'd1; 
                    endcase
                5'b00??0: //even months (30 days); April and June; 4, 6
                  casex(day_reg)
                    8'h30: day_reg <= 8'd01;
                    8'h?9: day_reg <= {(day_reg[5:4]+2'h1),4'h0}; //(Apr 09 --> Apr 10)
                    default: day_reg <= day_reg + 8'd01;
                  endcase
                5'b00??1: //odd months (31 days); January, March, May and July; 1, 3, 5, 7
                  casex(day_reg)
                    8'h31: day_reg <= 8'd01;
                    8'h?9: day_reg <= {(day_reg[5:4]+2'h1),4'h0}; //(Jan 09 --> Jan 10)
                    default: day_reg <= day_reg + 8'd01;
                  endcase
                5'b????0: //even months (31 days); August, October, December; 8, 10, 12
                  casex(day_reg)
                    8'h31: day_reg <= 8'd01;
                    8'h?9: day_reg <= {(day_reg[5:4]+2'h1),4'h0}; //(Aug 09 --> Aug 10)
                    default: day_reg <= day_reg + 8'd1;
                  endcase
                5'b????1: //odd months (30 days); September, November; 9, 11
                  casex(day_reg)
                    8'h30: day_reg <= 8'd01;
                    8'h?9: day_reg <= {(day_reg[5:4]+2'h1),4'h0}; //(Sep 09 --> Sep 10)
                    default: day_reg <= day_reg + 8'd1;
                  endcase
              endcase
            end
        end
    end
endmodule

features/TBdate.v
`timescale 1ns / 1ps

module datetb;

  // Parameters
  parameter CLK_PERIOD = 10; // Clock period in ns
  
  // Signals
  reg clk;
  reg [7:0] hour_in;
  reg [23:0] date_in;
  reg [1:0] date_ow;
  wire [23:0] date_out;

  // Instantiate the clockCalendarDec2 module
  datemodule dut (
    .clk(clk),
    .hour_in(hour_in),
    .date_in(date_in),
    .date_mode(date_ow),
    .date_out(date_out)
  );

  // Clock generation
  always #((CLK_PERIOD/2)) clk = ~clk;

  // Test scenarios
  initial begin
    $monitor("Time: %0t, Hour: %h, Date: %b, Date Overwrite: %b, New Date: %b", $time, hour_in, date_in, date_ow, date_out);
    $dumpfile("date.vcd");
    $dumpvars(0, datetb);
    
    // Initialize signals
    clk = 0;
    hour_in = 8'h0;
    date_in = 24'h000000;
    date_ow = 0;
    
    // Apply some scenarios
    // Test normal day increment
    #50;
    hour_in = 8'h01;
    #50;
    hour_in = 8'h02;
    #50;
    hour_in = 8'h03;
    // Set date overwrite to change date
    date_ow = 2;
    #10;
    date_in = 23'h3_1_1_2_0_4;
    #20
    date_ow = 0;
    #50;
    hour_in = 8'h23;
    #10
    hour_in = 8'h0;
    #100
    $finish;
  end

endmodule

features/date.vcd
$date
	Thu May  2 16:01:03 2024
$end
$version
	Icarus Verilog
$end
$timescale
	1ps
$end
$scope module datetb $end
$var wire 24 ! date_out [23:0] $end
$var reg 1 " clk $end
$var reg 24 # date_in [23:0] $end
$var reg 2 $ date_ow [1:0] $end
$var reg 8 % hour_in [7:0] $end
$scope module dut $end
$var wire 1 " clk $end
$var wire 24 & date_in [23:0] $end
$var wire 2 ' date_mode [1:0] $end
$var wire 8 ( hour_in [7:0] $end
$var wire 1 ) new_month $end
$var wire 1 * new_year $end
$var wire 8 + year_in [7:0] $end
$var wire 8 , month_in [7:0] $end
$var wire 8 - day_in [7:0] $end
$var wire 24 . date_out [23:0] $end
$var reg 8 / day_reg [7:0] $end
$var reg 8 0 day_reg_del [7:0] $end
$var reg 8 1 hour_reg [7:0] $end
$var reg 8 2 month_reg [7:0] $end
$var reg 8 3 month_reg_del [7:0] $end
$var reg 1 4 new_day $end
$var reg 8 5 year_reg [7:0] $end
$upscope $end
$upscope $end
$enddefinitions $end
#0
$dumpvars
bx 5
x4
bx 3
bx 2
bx 1
bx 0
bx /
bx .
b0 -
b0 ,
b0 +
x*
x)
b0 (
b0 '
b0 &
b0 %
b0 $
b0 #
0"
bx !
$end
#5000
b0 1
1"
#10000
0"
#15000
04
1"
#20000
0"
#25000
1"
#30000
0"
#35000
1"
#40000
0"
#45000
1"
#50000
0"
b1 %
b1 (
#55000
b1 1
1"
#60000
0"
#65000
1"
#70000
0"
#75000
1"
#80000
0"
#85000
1"
#90000
0"
#95000
1"
#100000
0"
b10 %
b10 (
#105000
b10 1
1"
#110000
0"
#115000
1"
#120000
0"
#125000
1"
#130000
0"
#135000
1"
#140000
0"
#145000
1"
#150000
0"
b10 $
b10 '
b11 %
b11 (
#155000
0)
0*
b0 /
b0 2
b0 !
b0 .
b0 5
b11 1
1"
#160000
b110001 -
b10010 ,
b100 +
0"
b1100010001001000000100 #
b1100010001001000000100 &
#165000
b100 5
b10010 2
b1100010001001000000100 !
b1100010001001000000100 .
b110001 /
b0 3
b0 0
1"
#170000
0"
#175000
b10010 3
b110001 0
1"
#180000
0"
b0 $
b0 '
#185000
1"
#190000
0"
#195000
1"
#200000
0"
#205000
1"
#210000
0"
#215000
1"
#220000
0"
#225000
1"
#230000
0"
b100011 %
b100011 (
#235000
b100011 1
1"
#240000
0"
b0 %
b0 (
#245000
14
b0 1
1"
#250000
0"
#255000
1)
b10001001000000100 !
b10001001000000100 .
b1 /
04
1"
#260000
0"
#265000
1*
0)
b10000000100000100 !
b10000000100000100 .
b1 2
b1 0
1"
#270000
0"
#275000
0*
b10000000100000101 !
b10000000100000101 .
b101 5
b1 3
1"
