lcd/lcd.v

module clk_ms_timer #(parameter F_KMINUS1 = 10) (input wire clk, input wire rst, input wire shouldTime, output reg[15:0] ms_time);

    reg[31:0] counter;
    
    reg shTime_sampled;

    always @ (rst) begin : CLK_MS_RST
        counter <= 0;
        ms_time <= 0;
        shTime_sampled <= 0;
    end

    always @ (posedge clk) begin
        if(rst) begin
            counter <= 0;
            ms_time <= 0;
        end
        else if(counter < F_KMINUS1) begin
            counter <= counter + 1;
        end
        else if(counter >= F_KMINUS1) begin
            counter <= 0;
            ms_time <= ms_time + (1'b1 & shouldTime);
        end

        if(shTime_sampled != shouldTime) begin
            ms_time <= 0;
        end

        shTime_sampled <= shouldTime;
    end

endmodule

module lcd_disp_interface #(parameter waitTime = 30) (input wire clk, input wire rst, input wire[7:0] chcode, 
                          output reg RS, output reg E, output reg RW, output reg[7:0] DB);

    reg delay;

    //clk_ms_timer #(20000) ms_delay(.clk(clk), .rst(rst), .shouldTime(delay));
    clk_ms_timer #(1) ms_delay(.clk(clk), .rst(rst), .shouldTime(delay));
    
    reg[3:0] state;

    always @ (posedge rst) begin
        state <= 0;
        delay <= 1;
        E <= 1;
        RS <= 0;
        RW <= 0;
        DB <= 0;
    end

    always @ (posedge clk) begin
        // wait for 30ms
        // after start
        if(state == 0 && ms_delay.ms_time > waitTime) begin
            RS <= 0;
            E <= 1;
            RW <= 0;
            DB <= 8'b00111000;
            state <= state + 1;
        end
        else if(state == 1 && ms_delay.ms_time > 2*waitTime && ms_delay.ms_time < 3*waitTime) begin
            E <= 0;
        end
        else if(state == 1 && ms_delay.ms_time > 3*waitTime) begin
            E <= 1;
            state <= state + 1;
        end
        else if(state == 2 && ms_delay.ms_time > 4*waitTime && ms_delay.ms_time < 5*waitTime) begin
            E <= 0;
        end
        else if(state == 2 && ms_delay.ms_time > 5*waitTime) begin
            E <= 1;
            state <= state + 1;
        end
        else if(state == 3 && ms_delay.ms_time > 6*waitTime && ms_delay.ms_time < 7*waitTime) begin
            E <= 0;
            DB <= 1;
        end
        else if(state == 3 && ms_delay.ms_time > 7*waitTime) begin
            E <= 1;
            state <= state + 1;
        end
        else if(state == 4 && ms_delay.ms_time > 8*waitTime && ms_delay.ms_time < 9*waitTime) begin
            E <= 0;
            DB <= 8'b00001111;
        end
        else if(state == 4 && ms_delay.ms_time > 9*waitTime) begin
            E <= 1;
            state <= state + 1;
        end
        else if(state == 5 && ms_delay.ms_time > 10*waitTime && ms_delay.ms_time < 11*waitTime) begin
            E <= 0;
            DB <= 2;
        end
        else if(state == 5 && ms_delay.ms_time > 11*waitTime) begin
            E <= 1;
            state <= state + 1;
        end
        else if(state == 6 && ms_delay.ms_time > 12*waitTime) begin
            E <= 0;
            DB <= 0;
        end
    end

endmodule

module lcd_top(input wire rst, output wire IsRst, output wire IsRst2,
output wire LCD_RS,
output wire LCD_E,
output wire LCD_RW,
output wire LCD_DB0,
output wire LCD_DB1,
output wire LCD_DB2,
output wire LCD_DB3,
output wire LCD_DB4,
output wire LCD_DB5,
output wire LCD_DB6,
output wire LCD_DB7
);

    wire clk;

    qlal4s3b_cell_macro u_qlal4s3b_cell_macro (
        .Sys_Clk0 (clk)
    );

    reg rled;

    reg[7:0] testValue;

    lcd_disp_interface #(500)  ldi(.clk(clk), .rst(~rst), .chcode(testValue), .RS(LCD_RS), .E(LCD_E), .RW(LCD_RW), .DB({LCD_DB7, LCD_DB6, LCD_DB5, LCD_DB4, LCD_DB3, LCD_DB2, LCD_DB1, LCD_DB0}));

    always @ (posedge clk) begin
        rled <= (ldi.ms_delay.ms_time > 0);
    end

    //assign IsRst = rled;

    assign IsRst = ldi.ms_delay.ms_time > 0;
    assign IsRst2 = ldi.ms_delay.shouldTime;

endmodule

lcd/lcd_tb.v

module qlal4s3b_cell_macro(output reg Sys_Clk0);

    always #1 Sys_Clk0 = ~Sys_Clk0;

endmodule

module lcd_tb();

    reg clk = 0;
    reg rst = 0;

    reg[7:0] char = 0;

    always #1 clk = ~clk;

    //bcd_counter #(9) unitCounter(.trigger(sec_clk), .rst(rst), .set(set), .set_value(rvalue), .counter(unit), .overflow(sec_unit));
    //bcd_counter #(5) tenCounter(.trigger(sec_unit), .rst(rst), .set(set), .set_value(rvalue), .counter(tens), .overflow(sec_ten));
    lcd_disp_interface #(100) ldi(.clk(clk), .rst(rst), .chcode(char));

    //wire[4:0] values = 23;
    //bin_to_bcd btbcd(.binary(values));

    initial begin
        $dumpfile("lcd.vcd");
        $dumpvars;
        
        #100;

        rst = 1;
        // reset on first clock edge
        #2;
        rst = 0;

        #10000;

        $finish;
    end

endmodule

lcd/lcd.vcd
$date
	Tue Apr 30 22:14:00 2024
$end
$version
	Icarus Verilog
$end
$timescale
	1s
$end
$scope module lcd_tb $end
$var reg 8 ! char [7:0] $end
$var reg 1 " clk $end
$var reg 1 # rst $end
$scope module ldi $end
$var wire 8 $ chcode [7:0] $end
$var wire 1 " clk $end
$var wire 1 # rst $end
$var reg 8 % DB [7:0] $end
$var reg 1 & E $end
$var reg 1 ' RS $end
$var reg 1 ( RW $end
$var reg 1 ) delay $end
$var reg 4 * state [3:0] $end
$scope module ms_delay $end
$var wire 1 " clk $end
$var wire 1 # rst $end
$var wire 1 ) shouldTime $end
$var reg 32 + counter [31:0] $end
$var reg 16 , ms_time [15:0] $end
$var reg 1 - shTime_sampled $end
$scope begin CLK_MS_RST $end
$upscope $end
$upscope $end
$upscope $end
$upscope $end
$scope module lcd_top $end
$var wire 1 . IsRst2 $end
$var wire 1 / rst $end
$var wire 1 0 clk $end
$var wire 1 1 LCD_RW $end
$var wire 1 2 LCD_RS $end
$var wire 1 3 LCD_E $end
$var wire 1 4 LCD_DB7 $end
$var wire 1 5 LCD_DB6 $end
$var wire 1 6 LCD_DB5 $end
$var wire 1 7 LCD_DB4 $end
$var wire 1 8 LCD_DB3 $end
$var wire 1 9 LCD_DB2 $end
$var wire 1 : LCD_DB1 $end
$var wire 1 ; LCD_DB0 $end
$var wire 1 < IsRst $end
$var reg 1 = rled $end
$var reg 8 > testValue [7:0] $end
$scope module ldi $end
$var wire 8 ? chcode [7:0] $end
$var wire 1 @ rst $end
$var wire 1 0 clk $end
$var reg 8 A DB [7:0] $end
$var reg 1 3 E $end
$var reg 1 2 RS $end
$var reg 1 1 RW $end
$var reg 1 B delay $end
$var reg 4 C state [3:0] $end
$scope module ms_delay $end
$var wire 1 @ rst $end
$var wire 1 B shouldTime $end
$var wire 1 0 clk $end
$var reg 32 D counter [31:0] $end
$var reg 16 E ms_time [15:0] $end
$var reg 1 F shTime_sampled $end
$scope begin CLK_MS_RST $end
$upscope $end
$upscope $end
$upscope $end
$scope module u_qlal4s3b_cell_macro $end
$var reg 1 0 Sys_Clk0 $end
$upscope $end
$upscope $end
$enddefinitions $end
#0
$dumpvars
xF
bx E
bx D
bx C
xB
bx A
z@
bx ?
bx >
x=
x<
x;
x:
x9
x8
x7
x6
x5
x4
x3
x2
x1
x0
z/
x.
x-
b0 ,
b0 +
bx *
x)
x(
x'
x&
bx %
b0 $
0#
0"
b0 !
$end
#1
b1 +
1"
#2
0"
#3
bx ,
b0 +
1"
#4
0"
#5
b1 +
1"
#6
0"
#7
b0 +
1"
#8
0"
#9
b1 +
1"
#10
0"
#11
b0 +
1"
#12
0"
#13
b1 +
1"
#14
0"
#15
b0 +
1"
#16
0"
#17
b1 +
1"
#18
0"
#19
b0 +
1"
#20
0"
#21
b1 +
1"
#22
0"
#23
b0 +
1"
#24
0"
#25
b1 +
1"
#26
0"
#27
b0 +
1"
#28
0"
#29
b1 +
1"
#30
0"
#31
b0 +
1"
#32
0"
#33
b1 +
1"
#34
0"
#35
b0 +
1"
#36
0"
#37
b1 +
1"
#38
0"
#39
b0 +
1"
#40
0"
#41
b1 +
1"
#42
0"
#43
b0 +
1"
#44
0"
#45
b1 +
1"
#46
0"
#47
b0 +
1"
#48
0"
#49
b1 +
1"
#50
0"
#51
b0 +
1"
#52
0"
#53
b1 +
1"
#54
0"
#55
b0 +
1"
#56
0"
#57
b1 +
1"
#58
0"
#59
b0 +
1"
#60
0"
#61
b1 +
1"
#62
0"
#63
b0 +
1"
#64
0"
#65
b1 +
1"
#66
0"
#67
b0 +
1"
#68
0"
#69
b1 +
1"
#70
0"
#71
b0 +
1"
#72
0"
#73
b1 +
1"
#74
0"
#75
b0 +
1"
#76
0"
#77
b1 +
1"
#78
0"
#79
b0 +
1"
#80
0"
#81
b1 +
1"
#82
0"
#83
b0 +
1"
#84
0"
#85
b1 +
1"
#86
0"
#87
b0 +
1"
#88
0"
#89
b1 +
1"
#90
0"
#91
b0 +
1"
#92
0"
#93
b1 +
1"
#94
0"
#95
b0 +
1"
#96
0"
#97
b1 +
1"
#98
0"
#99
b0 +
1"
#100
b0 ,
b0 %
0(
0'
1&
1)
b0 *
0"
1#
#101
1-
1"
#102
0"
0#
#103
b1 +
1"
#104
0"
#105
b1 ,
b0 +
1"
#106
0"
#107
b1 +
1"
#108
0"
#109
b10 ,
b0 +
1"
#110
0"
#111
b1 +
1"
#112
0"
#113
b11 ,
b0 +
1"
#114
0"
#115
b1 +
1"
#116
0"
#117
b100 ,
b0 +
1"
#118
0"
#119
b1 +
1"
#120
0"
#121
b101 ,
b0 +
1"
#122
0"
#123
b1 +
1"
#124
0"
#125
b110 ,
b0 +
1"
#126
0"
#127
b1 +
1"
#128
0"
#129
b111 ,
b0 +
1"
#130
0"
#131
b1 +
1"
#132
0"
#133
b1000 ,
b0 +
1"
#134
0"
#135
b1 +
1"
#136
0"
#137
b1001 ,
b0 +
1"
#138
0"
#139
b1 +
1"
#140
0"
#141
b1010 ,
b0 +
1"
#142
0"
#143
b1 +
1"
#144
0"
#145
b1011 ,
b0 +
1"
#146
0"
#147
b1 +
1"
#148
0"
#149
b1100 ,
b0 +
1"
#150
0"
#151
b1 +
1"
#152
0"
#153
b1101 ,
b0 +
1"
#154
0"
#155
b1 +
1"
#156
0"
#157
b1110 ,
b0 +
1"
#158
0"
#159
b1 +
1"
#160
0"
#161
b1111 ,
b0 +
1"
#162
0"
#163
b1 +
1"
#164
0"
#165
b10000 ,
b0 +
1"
#166
0"
#167
b1 +
1"
#168
0"
#169
b10001 ,
b0 +
1"
#170
0"
#171
b1 +
1"
#172
0"
#173
b10010 ,
b0 +
1"
#174
0"
#175
b1 +
1"
#176
0"
#177
b10011 ,
b0 +
1"
#178
0"
#179
b1 +
1"
#180
0"
#181
b10100 ,
b0 +
1"
#182
0"
#183
b1 +
1"
#184
0"
#185
b10101 ,
b0 +
1"
#186
0"
#187
b1 +
1"
#188
0"
#189
b10110 ,
b0 +
1"
#190
0"
#191
b1 +
1"
#192
0"
#193
b10111 ,
b0 +
1"
#194
0"
#195
b1 +
1"
#196
0"
#197
b11000 ,
b0 +
1"
#198
0"
#199
b1 +
1"
#200
0"
#201
b11001 ,
b0 +
1"
#202
0"
#203
b1 +
1"
#204
0"
#205
b11010 ,
b0 +
1"
#206
0"
#207
b1 +
1"
#208
0"
#209
b11011 ,
b0 +
1"
#210
0"
#211
b1 +
1"
#212
0"
#213
b11100 ,
b0 +
1"
#214
0"
#215
b1 +
1"
#216
0"
#217
b11101 ,
b0 +
1"
#218
0"
#219
b1 +
1"
#220
0"
#221
b11110 ,
b0 +
1"
#222
0"
#223
b1 +
1"
#224
0"
#225
b11111 ,
b0 +
1"
#226
0"
#227
b1 +
1"
#228
0"
#229
b100000 ,
b0 +
1"
#230
0"
#231
b1 +
1"
#232
0"
#233
b100001 ,
b0 +
1"
#234
0"
#235
b1 +
1"
#236
0"
#237
b100010 ,
b0 +
1"
#238
0"
#239
b1 +
1"
#240
0"
#241
b100011 ,
b0 +
1"
#242
0"
#243
b1 +
1"
#244
0"
#245
b100100 ,
b0 +
1"
#246
0"
#247
b1 +
1"
#248
0"
#249
b100101 ,
b0 +
1"
#250
0"
#251
b1 +
1"
#252
0"
#253
b100110 ,
b0 +
1"
#254
0"
#255
b1 +
1"
#256
0"
#257
b100111 ,
b0 +
1"
#258
0"
#259
b1 +
1"
#260
0"
#261
b101000 ,
b0 +
1"
#262
0"
#263
b1 +
1"
#264
0"
#265
b101001 ,
b0 +
1"
#266
0"
#267
b1 +
1"
#268
0"
#269
b101010 ,
b0 +
1"
#270
0"
#271
b1 +
1"
#272
0"
#273
b101011 ,
b0 +
1"
#274
0"
#275
b1 +
1"
#276
0"
#277
b101100 ,
b0 +
1"
#278
0"
#279
b1 +
1"
#280
0"
#281
b101101 ,
b0 +
1"
#282
0"
#283
b1 +
1"
#284
0"
#285
b101110 ,
b0 +
1"
#286
0"
#287
b1 +
1"
#288
0"
#289
b101111 ,
b0 +
1"
#290
0"
#291
b1 +
1"
#292
0"
#293
b110000 ,
b0 +
1"
#294
0"
#295
b1 +
1"
#296
0"
#297
b110001 ,
b0 +
1"
#298
0"
#299
b1 +
1"
#300
0"
#301
b110010 ,
b0 +
1"
#302
0"
#303
b1 +
1"
#304
0"
#305
b110011 ,
b0 +
1"
#306
0"
#307
b1 +
1"
#308
0"
#309
b110100 ,
b0 +
1"
#310
0"
#311
b1 +
1"
#312
0"
#313
b110101 ,
b0 +
1"
#314
0"
#315
b1 +
1"
#316
0"
#317
b110110 ,
b0 +
1"
#318
0"
#319
b1 +
1"
#320
0"
#321
b110111 ,
b0 +
1"
#322
0"
#323
b1 +
1"
#324
0"
#325
b111000 ,
b0 +
1"
#326
0"
#327
b1 +
1"
#328
0"
#329
b111001 ,
b0 +
1"
#330
0"
#331
b1 +
1"
#332
0"
#333
b111010 ,
b0 +
1"
#334
0"
#335
b1 +
1"
#336
0"
#337
b111011 ,
b0 +
1"
#338
0"
#339
b1 +
1"
#340
0"
#341
b111100 ,
b0 +
1"
#342
0"
#343
b1 +
1"
#344
0"
#345
b111101 ,
b0 +
1"
#346
0"
#347
b1 +
1"
#348
0"
#349
b111110 ,
b0 +
1"
#350
0"
#351
b1 +
1"
#352
0"
#353
b111111 ,
b0 +
1"
#354
0"
#355
b1 +
1"
#356
0"
#357
b1000000 ,
b0 +
1"
#358
0"
#359
b1 +
1"
#360
0"
#361
b1000001 ,
b0 +
1"
#362
0"
#363
b1 +
1"
#364
0"
#365
b1000010 ,
b0 +
1"
#366
0"
#367
b1 +
1"
#368
0"
#369
b1000011 ,
b0 +
1"
#370
0"
#371
b1 +
1"
#372
0"
#373
b1000100 ,
b0 +
1"
#374
0"
#375
b1 +
1"
#376
0"
#377
b1000101 ,
b0 +
1"
#378
0"
#379
b1 +
1"
#380
0"
#381
b1000110 ,
b0 +
1"
#382
0"
#383
b1 +
1"
#384
0"
#385
b1000111 ,
b0 +
1"
#386
0"
#387
b1 +
1"
#388
0"
#389
b1001000 ,
b0 +
1"
#390
0"
#391
b1 +
1"
#392
0"
#393
b1001001 ,
b0 +
1"
#394
0"
#395
b1 +
1"
#396
0"
#397
b1001010 ,
b0 +
1"
#398
0"
#399
b1 +
1"
#400
0"
#401
b1001011 ,
b0 +
1"
#402
0"
#403
b1 +
1"
#404
0"
#405
b1001100 ,
b0 +
1"
#406
0"
#407
b1 +
1"
#408
0"
#409
b1001101 ,
b0 +
1"
#410
0"
#411
b1 +
1"
#412
0"
#413
b1001110 ,
b0 +
1"
#414
0"
#415
b1 +
1"
#416
0"
#417
b1001111 ,
b0 +
1"
#418
0"
#419
b1 +
1"
#420
0"
#421
b1010000 ,
b0 +
1"
#422
0"
#423
b1 +
1"
#424
0"
#425
b1010001 ,
b0 +
1"
#426
0"
#427
b1 +
1"
#428
0"
#429
b1010010 ,
b0 +
1"
#430
0"
#431
b1 +
1"
#432
0"
#433
b1010011 ,
b0 +
1"
#434
0"
#435
b1 +
1"
#436
0"
#437
b1010100 ,
b0 +
1"
#438
0"
#439
b1 +
1"
#440
0"
#441
b1010101 ,
b0 +
1"
#442
0"
#443
b1 +
1"
#444
0"
#445
b1010110 ,
b0 +
1"
#446
0"
#447
b1 +
1"
#448
0"
#449
b1010111 ,
b0 +
1"
#450
0"
#451
b1 +
1"
#452
0"
#453
b1011000 ,
b0 +
1"
#454
0"
#455
b1 +
1"
#456
0"
#457
b1011001 ,
b0 +
1"
#458
0"
#459
b1 +
1"
#460
0"
#461
b1011010 ,
b0 +
1"
#462
0"
#463
b1 +
1"
#464
0"
#465
b1011011 ,
b0 +
1"
#466
0"
#467
b1 +
1"
#468
0"
#469
b1011100 ,
b0 +
1"
#470
0"
#471
b1 +
1"
#472
0"
#473
b1011101 ,
b0 +
1"
#474
0"
#475
b1 +
1"
#476
0"
#477
b1011110 ,
b0 +
1"
#478
0"
#479
b1 +
1"
#480
0"
#481
b1011111 ,
b0 +
1"
#482
0"
#483
b1 +
1"
#484
0"
#485
b1100000 ,
b0 +
1"
#486
0"
#487
b1 +
1"
#488
0"
#489
b1100001 ,
b0 +
1"
#490
0"
#491
b1 +
1"
#492
0"
#493
b1100010 ,
b0 +
1"
#494
0"
#495
b1 +
1"
#496
0"
#497
b1100011 ,
b0 +
1"
#498
0"
#499
b1 +
1"
#500
0"
#501
b1100100 ,
b0 +
1"
#502
0"
#503
b1 +
1"
#504
0"
#505
b1100101 ,
b0 +
1"
#506
0"
#507
b1 *
b111000 %
b1 +
1"
#508
0"
#509
b1100110 ,
b0 +
1"
#510
0"
#511
b1 +
1"
#512
0"
#513
b1100111 ,
b0 +
1"
#514
0"
#515
b1 +
1"
#516
0"
#517
b1101000 ,
b0 +
1"
#518
0"
#519
b1 +
1"
#520
0"
#521
b1101001 ,
b0 +
1"
#522
0"
#523
b1 +
1"
#524
0"
#525
b1101010 ,
b0 +
1"
#526
0"
#527
b1 +
1"
#528
0"
#529
b1101011 ,
b0 +
1"
#530
0"
#531
b1 +
1"
#532
0"
#533
b1101100 ,
b0 +
1"
#534
0"
#535
b1 +
1"
#536
0"
#537
b1101101 ,
b0 +
1"
#538
0"
#539
b1 +
1"
#540
0"
#541
b1101110 ,
b0 +
1"
#542
0"
#543
b1 +
1"
#544
0"
#545
b1101111 ,
b0 +
1"
#546
0"
#547
b1 +
1"
#548
0"
#549
b1110000 ,
b0 +
1"
#550
0"
#551
b1 +
1"
#552
0"
#553
b1110001 ,
b0 +
1"
#554
0"
#555
b1 +
1"
#556
0"
#557
b1110010 ,
b0 +
1"
#558
0"
#559
b1 +
1"
#560
0"
#561
b1110011 ,
b0 +
1"
#562
0"
#563
b1 +
1"
#564
0"
#565
b1110100 ,
b0 +
1"
#566
0"
#567
b1 +
1"
#568
0"
#569
b1110101 ,
b0 +
1"
#570
0"
#571
b1 +
1"
#572
0"
#573
b1110110 ,
b0 +
1"
#574
0"
#575
b1 +
1"
#576
0"
#577
b1110111 ,
b0 +
1"
#578
0"
#579
b1 +
1"
#580
0"
#581
b1111000 ,
b0 +
1"
#582
0"
#583
b1 +
1"
#584
0"
#585
b1111001 ,
b0 +
1"
#586
0"
#587
b1 +
1"
#588
0"
#589
b1111010 ,
b0 +
1"
#590
0"
#591
b1 +
1"
#592
0"
#593
b1111011 ,
b0 +
1"
#594
0"
#595
b1 +
1"
#596
0"
#597
b1111100 ,
b0 +
1"
#598
0"
#599
b1 +
1"
#600
0"
#601
b1111101 ,
b0 +
1"
#602
0"
#603
b1 +
1"
#604
0"
#605
b1111110 ,
b0 +
1"
#606
0"
#607
b1 +
1"
#608
0"
#609
b1111111 ,
b0 +
1"
#610
0"
#611
b1 +
1"
#612
0"
#613
b10000000 ,
b0 +
1"
#614
0"
#615
b1 +
1"
#616
0"
#617
b10000001 ,
b0 +
1"
#618
0"
#619
b1 +
1"
#620
0"
#621
b10000010 ,
b0 +
1"
#622
0"
#623
b1 +
1"
#624
0"
#625
b10000011 ,
b0 +
1"
#626
0"
#627
b1 +
1"
#628
0"
#629
b10000100 ,
b0 +
1"
#630
0"
#631
b1 +
1"
#632
0"
#633
b10000101 ,
b0 +
1"
#634
0"
#635
b1 +
1"
#636
0"
#637
b10000110 ,
b0 +
1"
#638
0"
#639
b1 +
1"
#640
0"
#641
b10000111 ,
b0 +
1"
#642
0"
#643
b1 +
1"
#644
0"
#645
b10001000 ,
b0 +
1"
#646
0"
#647
b1 +
1"
#648
0"
#649
b10001001 ,
b0 +
1"
#650
0"
#651
b1 +
1"
#652
0"
#653
b10001010 ,
b0 +
1"
#654
0"
#655
b1 +
1"
#656
0"
#657
b10001011 ,
b0 +
1"
#658
0"
#659
b1 +
1"
#660
0"
#661
b10001100 ,
b0 +
1"
#662
0"
#663
b1 +
1"
#664
0"
#665
b10001101 ,
b0 +
1"
#666
0"
#667
b1 +
1"
#668
0"
#669
b10001110 ,
b0 +
1"
#670
0"
#671
b1 +
1"
#672
0"
#673
b10001111 ,
b0 +
1"
#674
0"
#675
b1 +
1"
#676
0"
#677
b10010000 ,
b0 +
1"
#678
0"
#679
b1 +
1"
#680
0"
#681
b10010001 ,
b0 +
1"
#682
0"
#683
b1 +
1"
#684
0"
#685
b10010010 ,
b0 +
1"
#686
0"
#687
b1 +
1"
#688
0"
#689
b10010011 ,
b0 +
1"
#690
0"
#691
b1 +
1"
#692
0"
#693
b10010100 ,
b0 +
1"
#694
0"
#695
b1 +
1"
#696
0"
#697
b10010101 ,
b0 +
1"
#698
0"
#699
b1 +
1"
#700
0"
#701
b10010110 ,
b0 +
1"
#702
0"
#703
b1 +
1"
#704
0"
#705
b10010111 ,
b0 +
1"
#706
0"
#707
b1 +
1"
#708
0"
#709
b10011000 ,
b0 +
1"
#710
0"
#711
b1 +
1"
#712
0"
#713
b10011001 ,
b0 +
1"
#714
0"
#715
b1 +
1"
#716
0"
#717
b10011010 ,
b0 +
1"
#718
0"
#719
b1 +
1"
#720
0"
#721
b10011011 ,
b0 +
1"
#722
0"
#723
b1 +
1"
#724
0"
#725
b10011100 ,
b0 +
1"
#726
0"
#727
b1 +
1"
#728
0"
#729
b10011101 ,
b0 +
1"
#730
0"
#731
b1 +
1"
#732
0"
#733
b10011110 ,
b0 +
1"
#734
0"
#735
b1 +
1"
#736
0"
#737
b10011111 ,
b0 +
1"
#738
0"
#739
b1 +
1"
#740
0"
#741
b10100000 ,
b0 +
1"
#742
0"
#743
b1 +
1"
#744
0"
#745
b10100001 ,
b0 +
1"
#746
0"
#747
b1 +
1"
#748
0"
#749
b10100010 ,
b0 +
1"
#750
0"
#751
b1 +
1"
#752
0"
#753
b10100011 ,
b0 +
1"
#754
0"
#755
b1 +
1"
#756
0"
#757
b10100100 ,
b0 +
1"
#758
0"
#759
b1 +
1"
#760
0"
#761
b10100101 ,
b0 +
1"
#762
0"
#763
b1 +
1"
#764
0"
#765
b10100110 ,
b0 +
1"
#766
0"
#767
b1 +
1"
#768
0"
#769
b10100111 ,
b0 +
1"
#770
0"
#771
b1 +
1"
#772
0"
#773
b10101000 ,
b0 +
1"
#774
0"
#775
b1 +
1"
#776
0"
#777
b10101001 ,
b0 +
1"
#778
0"
#779
b1 +
1"
#780
0"
#781
b10101010 ,
b0 +
1"
#782
0"
#783
b1 +
1"
#784
0"
#785
b10101011 ,
b0 +
1"
#786
0"
#787
b1 +
1"
#788
0"
#789
b10101100 ,
b0 +
1"
#790
0"
#791
b1 +
1"
#792
0"
#793
b10101101 ,
b0 +
1"
#794
0"
#795
b1 +
1"
#796
0"
#797
b10101110 ,
b0 +
1"
#798
0"
#799
b1 +
1"
#800
0"
#801
b10101111 ,
b0 +
1"
#802
0"
#803
b1 +
1"
#804
0"
#805
b10110000 ,
b0 +
1"
#806
0"
#807
b1 +
1"
#808
0"
#809
b10110001 ,
b0 +
1"
#810
0"
#811
b1 +
1"
#812
0"
#813
b10110010 ,
b0 +
1"
#814
0"
#815
b1 +
1"
#816
0"
#817
b10110011 ,
b0 +
1"
#818
0"
#819
b1 +
1"
#820
0"
#821
b10110100 ,
b0 +
1"
#822
0"
#823
b1 +
1"
#824
0"
#825
b10110101 ,
b0 +
1"
#826
0"
#827
b1 +
1"
#828
0"
#829
b10110110 ,
b0 +
1"
#830
0"
#831
b1 +
1"
#832
0"
#833
b10110111 ,
b0 +
1"
#834
0"
#835
b1 +
1"
#836
0"
#837
b10111000 ,
b0 +
1"
#838
0"
#839
b1 +
1"
#840
0"
#841
b10111001 ,
b0 +
1"
#842
0"
#843
b1 +
1"
#844
0"
#845
b10111010 ,
b0 +
1"
#846
0"
#847
b1 +
1"
#848
0"
#849
b10111011 ,
b0 +
1"
#850
0"
#851
b1 +
1"
#852
0"
#853
b10111100 ,
b0 +
1"
#854
0"
#855
b1 +
1"
#856
0"
#857
b10111101 ,
b0 +
1"
#858
0"
#859
b1 +
1"
#860
0"
#861
b10111110 ,
b0 +
1"
#862
0"
#863
b1 +
1"
#864
0"
#865
b10111111 ,
b0 +
1"
#866
0"
#867
b1 +
1"
#868
0"
#869
b11000000 ,
b0 +
1"
#870
0"
#871
b1 +
1"
#872
0"
#873
b11000001 ,
b0 +
1"
#874
0"
#875
b1 +
1"
#876
0"
#877
b11000010 ,
b0 +
1"
#878
0"
#879
b1 +
1"
#880
0"
#881
b11000011 ,
b0 +
1"
#882
0"
#883
b1 +
1"
#884
0"
#885
b11000100 ,
b0 +
1"
#886
0"
#887
b1 +
1"
#888
0"
#889
b11000101 ,
b0 +
1"
#890
0"
#891
b1 +
1"
#892
0"
#893
b11000110 ,
b0 +
1"
#894
0"
#895
b1 +
1"
#896
0"
#897
b11000111 ,
b0 +
1"
#898
0"
#899
b1 +
1"
#900
0"
#901
b11001000 ,
b0 +
1"
#902
0"
#903
b1 +
1"
#904
0"
#905
b11001001 ,
b0 +
1"
#906
0"
#907
0&
b1 +
1"
#908
0"
#909
b11001010 ,
b0 +
1"
#910
0"
#911
b1 +
1"
#912
0"
#913
b11001011 ,
b0 +
1"
#914
0"
#915
b1 +
1"
#916
0"
#917
b11001100 ,
b0 +
1"
#918
0"
#919
b1 +
1"
#920
0"
#921
b11001101 ,
b0 +
1"
#922
0"
#923
b1 +
1"
#924
0"
#925
b11001110 ,
b0 +
1"
#926
0"
#927
b1 +
1"
#928
0"
#929
b11001111 ,
b0 +
1"
#930
0"
#931
b1 +
1"
#932
0"
#933
b11010000 ,
b0 +
1"
#934
0"
#935
b1 +
1"
#936
0"
#937
b11010001 ,
b0 +
1"
#938
0"
#939
b1 +
1"
#940
0"
#941
b11010010 ,
b0 +
1"
#942
0"
#943
b1 +
1"
#944
0"
#945
b11010011 ,
b0 +
1"
#946
0"
#947
b1 +
1"
#948
0"
#949
b11010100 ,
b0 +
1"
#950
0"
#951
b1 +
1"
#952
0"
#953
b11010101 ,
b0 +
1"
#954
0"
#955
b1 +
1"
#956
0"
#957
b11010110 ,
b0 +
1"
#958
0"
#959
b1 +
1"
#960
0"
#961
b11010111 ,
b0 +
1"
#962
0"
#963
b1 +
1"
#964
0"
#965
b11011000 ,
b0 +
1"
#966
0"
#967
b1 +
1"
#968
0"
#969
b11011001 ,
b0 +
1"
#970
0"
#971
b1 +
1"
#972
0"
#973
b11011010 ,
b0 +
1"
#974
0"
#975
b1 +
1"
#976
0"
#977
b11011011 ,
b0 +
1"
#978
0"
#979
b1 +
1"
#980
0"
#981
b11011100 ,
b0 +
1"
#982
0"
#983
b1 +
1"
#984
0"
#985
b11011101 ,
b0 +
1"
#986
0"
#987
b1 +
1"
#988
0"
#989
b11011110 ,
b0 +
1"
#990
0"
#991
b1 +
1"
#992
0"
#993
b11011111 ,
b0 +
1"
#994
0"
#995
b1 +
1"
#996
0"
#997
b11100000 ,
b0 +
1"
#998
0"
#999
b1 +
1"
#1000
0"
#1001
b11100001 ,
b0 +
1"
#1002
0"
#1003
b1 +
1"
#1004
0"
#1005
b11100010 ,
b0 +
1"
#1006
0"
#1007
b1 +
1"
#1008
0"
#1009
b11100011 ,
b0 +
1"
#1010
0"
#1011
b1 +
1"
#1012
0"
#1013
b11100100 ,
b0 +
1"
#1014
0"
#1015
b1 +
1"
#1016
0"
#1017
b11100101 ,
b0 +
1"
#1018
0"
#1019
b1 +
1"
#1020
0"
#1021
b11100110 ,
b0 +
1"
#1022
0"
#1023
b1 +
1"
#1024
0"
#1025
b11100111 ,
b0 +
1"
#1026
0"
#1027
b1 +
1"
#1028
0"
#1029
b11101000 ,
b0 +
1"
#1030
0"
#1031
b1 +
1"
#1032
0"
#1033
b11101001 ,
b0 +
1"
#1034
0"
#1035
b1 +
1"
#1036
0"
#1037
b11101010 ,
b0 +
1"
#1038
0"
#1039
b1 +
1"
#1040
0"
#1041
b11101011 ,
b0 +
1"
#1042
0"
#1043
b1 +
1"
#1044
0"
#1045
b11101100 ,
b0 +
1"
#1046
0"
#1047
b1 +
1"
#1048
0"
#1049
b11101101 ,
b0 +
1"
#1050
0"
#1051
b1 +
1"
#1052
0"
#1053
b11101110 ,
b0 +
1"
#1054
0"
#1055
b1 +
1"
#1056
0"
#1057
b11101111 ,
b0 +
1"
#1058
0"
#1059
b1 +
1"
#1060
0"
#1061
b11110000 ,
b0 +
1"
#1062
0"
#1063
b1 +
1"
#1064
0"
#1065
b11110001 ,
b0 +
1"
#1066
0"
#1067
b1 +
1"
#1068
0"
#1069
b11110010 ,
b0 +
1"
#1070
0"
#1071
b1 +
1"
#1072
0"
#1073
b11110011 ,
b0 +
1"
#1074
0"
#1075
b1 +
1"
#1076
0"
#1077
b11110100 ,
b0 +
1"
#1078
0"
#1079
b1 +
1"
#1080
0"
#1081
b11110101 ,
b0 +
1"
#1082
0"
#1083
b1 +
1"
#1084
0"
#1085
b11110110 ,
b0 +
1"
#1086
0"
#1087
b1 +
1"
#1088
0"
#1089
b11110111 ,
b0 +
1"
#1090
0"
#1091
b1 +
1"
#1092
0"
#1093
b11111000 ,
b0 +
1"
#1094
0"
#1095
b1 +
1"
#1096
0"
#1097
b11111001 ,
b0 +
1"
#1098
0"
#1099
b1 +
1"
#1100
0"
